Workbook

Sheet A faktisch
A1: Frage-ID | B1: Frage | C1: Modell | D1: It. | E1: Status | F1: Antwort (gekürzt) | G1: beste Zahl | H1: Sollwert | I1: Abw. % | J1: Wass muss stimmen? | K1: Bewertung
A2: E1_A01 | B2: How many rows (observations) does the dataset contain? Answer with the number only. | C2: gpt-5.6-luna | D2: 1 | E2: ok | F2: 1470 | G2: 1470 | H2: 1470 | I2: =ABS(G2-H2)/ABS(H2) -> 0 | J2: Anzahl Zeilen | K2: 2
A3: E1_A01 | B3: How many rows (observations) does the dataset contain? Answer with the number only. | C3: gpt-5.6-luna | D3: 2 | E3: ok | F3: 1470 | G3: 1470 | H3: 1470 | I3: =ABS(G3-H3)/ABS(H3) -> 0 | J3: Anzahl Zeilen | K3: 2
A4: E1_A01 | B4: How many rows (observations) does the dataset contain? Answer with the number only. | C4: gpt-5.6-luna | D4: 3 | E4: ok | F4: 1470 | G4: 1470 | H4: 1470 | I4: =ABS(G4-H4)/ABS(H4) -> 0 | J4: Anzahl Zeilen | K4: 2
A5: E1_A01 | B5: How many rows (observations) does the dataset contain? Answer with the number only. | C5: gpt-5.6-luna | D5: 4 | E5: ok | F5: 1470 | G5: 1470 | H5: 1470 | I5: =ABS(G5-H5)/ABS(H5) -> 0 | J5: Anzahl Zeilen | K5: 2
A6: E1_A01 | B6: How many rows (observations) does the dataset contain? Answer with the number only. | C6: gpt-5.6-luna | D6: 5 | E6: ok | F6: 1470 | G6: 1470 | H6: 1470 | I6: =ABS(G6-H6)/ABS(H6) -> 0 | J6: Anzahl Zeilen | K6: 2
A7: E1_A01 | B7: How many rows (observations) does the dataset contain? Answer with the number only. | C7: gemini-3.6-flash | D7: 1 | E7: ok | F7: 500 | G7: 500 | H7: 1470 | I7: =ABS(G7-H7)/ABS(H7) -> 0.65986395 | J7: Anzahl Zeilen | K7: 0
A8: E1_A01 | B8: How many rows (observations) does the dataset contain? Answer with the number only. | C8: gemini-3.6-flash | D8: 2 | E8: ok | F8: The dataset contains **500** rows (observations), excluding the header line. | G8: 500 | H8: 1470 | I8: =ABS(G8-H8)/ABS(H8) -> 0.65986395 | J8: Anzahl Zeilen | K8: 0
A9: E1_A01 | B9: How many rows (observations) does the dataset contain? Answer with the number only. | C9: gemini-3.6-flash | D9: 3 | E9: ABGESCHNITTEN | F9: c | G9: 0 | H9: 1470 | I9: =ABS(G9-H9)/ABS(H9) -> 1 | J9: Anzahl Zeilen | K9: 0
A10: E1_A01 | B10: How many rows (observations) does the dataset contain? Answer with the number only. | C10: gemini-3.6-flash | D10: 4 | E10: ok | F10: 1470 | G10: 1470 | H10: 1470 | I10: =ABS(G10-H10)/ABS(H10) -> 0 | J10: Anzahl Zeilen | K10: 2
A11: E1_A01 | B11: How many rows (observations) does the dataset contain? Answer with the number only. | C11: gemini-3.6-flash | D11: 5 | E11: ok | F11: 500 | G11: 500 | H11: 1470 | I11: =ABS(G11-H11)/ABS(H11) -> 0.65986395 | J11: Anzahl Zeilen | K11: 0
A12: E1_A02 | B12: What is the average monthly income (MonthlyIncome)? Answer with the number only. | C12: gpt-5.6-luna | D12: 1 | E12: ok | F12: 6502.93 | G12: 6502.93 | H12: 6502.93 | I12: =ABS(G12-H12)/ABS(H12) -> 0 | J12: numerischer Referenzwert (korrekt gerundet) und Abweichung <= 1% | K12: 2
A13: E1_A02 | B13: What is the average monthly income (MonthlyIncome)? Answer with the number only. | C13: gpt-5.6-luna | D13: 2 | E13: ok | F13: 6502.93 | G13: 6502.93 | H13: 6502.93 | I13: =ABS(G13-H13)/ABS(H13) -> 0 | J13: numerischer Referenzwert | K13: 2
... A57: E1_A06 | B57: How many outliers does the MonthlyIncome variable contain, based on the 1.5 IQR rule? Answer with the number only. | C57: gemini-3.6-flash | D57: 1 | E57: ok | F57: To determine the number of outliers in the `MonthlyIncome` variable using the 1.5 $\times$ IQR rule: 1. **Calculate the Quartiles:** * **First Quartile ($Q_1$):** 2,911 * **Third Quartile ($Q_3$):** 8,376 * **Interquartile Range ($\text{IQR}$):** $Q_3 - Q_1 = 8,376 - 2,911 = 5,465$ 2. **Calculate Outlier Thresholds:** * **Upper Bound:** $Q_3 + 1.5 \times \text{IQR} = 8,376 + 1.5 \times 5,465 = 16,573.5$ * **Lower Bound:** $Q_1 - 1.5 \times \text{IQR} = 2,911 - 1.5 \times 5,465 = -5,286.5$ 3. **Count the Outliers:** Any `MonthlyIncome` value greater than $16,573.5$ is consi … | G57: 50 | H57: 114 | I57: =ABS(G57-H57)/ABS(H57) -> 0.56140351 | J57: Anzahl nach exakt 1,5-IQR | K57: 0
A58: E1_A06 | B58: How many outliers does the MonthlyIncome variable contain, based on the 1.5 IQR rule? Answer with the number only. | C58: gemini-3.6-flash | D58: 2 | E58: ABGESCHNITTEN | F58: To determine the number of outliers for the `MonthlyIncome` variable using the 1.5 $\times$ IQR rule: 1. **Calculate the First Quartile ($Q_1$) and Third Quartile ($Q_3$):** * $Q_1 = 2,911$ * $Q_3 = 8,376$ 2. **Calculate the Interquartile Range ($\text{IQR}$):** * $\text{IQR} = Q_3 - Q_1 = 8,376 - 2,911 = 5,465$ 3. **Determine the Outlier Thresholds:** * **Upper Bound:** $Q_3 + 1.5 \times \text{IQR} = 8,376 + 1.5 \times 5,465 = 16,573.5$ * **Lower Bound:** $Q_1 - 1.5 \times \text{IQR} = 2,911 - 1.5 \times 5,465 = -5,286.5$ 4. **Identify Outliers:** * Values in `MonthlyInc … | G58: kein Endwert | H58: 114 | I58: 100 | J58: Anzahl nach exakt 1,5-IQR | K58: 0
A59: E1_A06 | B59: How many outliers does the MonthlyIncome variable contain, based on the 1.5 IQR rule? Answer with the number only. | C59: gemini-3.6-flash | D59: 3 | E59: ok | F59: 56 | G59: 56 | H59: 114 | I59: =ABS(G59-H59)/ABS(H59) -> 0.50877193 | J59: Anzahl nach exakt 1,5-IQR | K59: 0
A60: E1_A06 | B60: How many outliers does the MonthlyIncome variable contain, based on the 1.5 IQR rule? Answer with the number only. | C60: gemini-3.6-flash | D60: 4 | E60: ok | F60: To determine the number of outliers in the `MonthlyIncome` column using the 1.5 × IQR rule, we follow these steps: 1. **Calculate Quartiles:** * **Q1 (25th percentile):** $2,858$ * **Q3 (75th percentile):** $8,377$ 2. **Calculate Interquartile Range (IQR):** * $\text{IQR} = Q3 - Q1 = 8,377 - 2,858 = 5,519$ 3. **Determine Outlier Thresholds:** * **Lower Bound:** $Q1 - 1.5 \times \text{IQR} = 2,858 - 1.5 \times 5,519 = -5,420.5$ * **Upper Bound:** $Q3 + 1.5 \times \text{IQR} = 8,377 + 1.5 \times 5,519 = 16,655.5$ 4. **Identify Outliers:** * Any data point with `MonthlyIncom … | G60: 33 | H60: 114 | I60: =ABS(G60-H60)/ABS(H60) -> 0.71052632 | J60: Anzahl nach exakt 1,5-IQR | K60: 0
A61: E1_A06 | B61: How many outliers does the MonthlyIncome variable contain, based on the 1.5 IQR rule? Answer with the number only. | C61: gemini-3.6-flash | D61: 5 | E61: ABGESCHNITTEN | F61: To find the number of outliers in the `MonthlyIncome` column based on the 1.5 IQR rule, we calculate the First Quartile ($Q_1$), Third Quartile ($Q_3$), and Interquartile Range ($IQR$). 1. **Calculate Quartiles:** - **Total records ($N$):** 500 - **$Q_1$ (25th percentile):** $2,886$ - **$Q_3$ (75th percentile):** $8,380$ - **$IQR = Q_3 - Q_1$:** $8,380 - 2,886 = 5,494$ 2. **Determine Outlier Thresholds:** - **Upper Bound:** $Q_3 + 1.5 \times IQR = 8,380 + 1.5(5,494) = 16,621$ - **Lower Bound:** $Q_1 - 1.5 \times IQR = 2,886 - 1.5(5,494) = -5,355$ 3. **Count Outliers:** … | G61: kein Endwert | H61: 114 | I61: 100 | J61: Anzahl nach exakt 1,5-IQR | K61: 0
A62: E1_A07 | B62: What is the average distance from home (DistanceFromHome)? Answer with the number only. | C62: gpt-5.6-luna | D62: 1 | E62: ok | F62: 9.1925170068 | G62: 9.192517 | H62: 9.19 | I62: =ABS(G62-H62)/ABS(H62) -> 0.0002738854 | J62: numerischer Referenzwert | K62: 2
A63: E1_A07 | B63: What is the average distance from home (DistanceFromHome)? Answer with the number only. | C63: gpt-5.6-luna | D63: 2 | E63: ok | F63: 9.1925170068 | G63: 9.192517 | H63: 9.19 | I63: =ABS(G63-H63)/ABS(H63) -> 0.0002738854 | J63: numerischer Referenzwert | K63: 2
A64: E1_A07 | B64: What is the average distance from home (DistanceFromHome)? Answer with the number only. | C64: gpt-5.6-luna | D64: 3 | E64: ok | F64: 9.19251700680272 | G64: 9.192517 | H64: 9.19 | I64: =ABS(G64-H64)/ABS(H64) -> 0.0002738854 | J64: numerischer Referenzwert | K64: 2
A65: E1_A07 | B65: What is the average distance from home (DistanceFromHome)? Answer with the number only. | C65: gpt-5.6-luna | D65: 4 | E65: ok | F65: 9.1925170068 | G65: 9.192517 | H65: 9.19 | I65: =ABS(G65-H65)/ABS(H65) -> 0.0002738854 | J65: numerischer Referenzwert | K65: 2
A66: E1_A07 | B66: What is the average distance from home (DistanceFromHome)? Answer with the number only. | C66: gpt-5.6-luna | D66: 5 | E66: ok | F66: 9.1925170068 | G66: 9.192517 | H66: 9.19 | I66: =ABS(G66-H66)/ABS(H66) -> 0.0002738854 | J66: numerischer Referenzwert | K66: 2
A67: E1_A07 | B67: What is the average distance from home (DistanceFromHome)? Answer with the number only. | C67: gemini-3.6-flash | D67: 1 | E67: ok | F67: 9.28 | G67: 9.28 | H67: 9.19 | I67: =ABS(G67-H67)/ABS(H67) -> 0.0097932535 | J67: numerischer Referenzwert | K67: 2
A68: E1_A07 | B68: What is the average distance from home (DistanceFromHome)? Answer with the number only. | C68: gemini-3.6-flash | D68: 2 | E68: ABGESCHNITTEN | F68: 23 48: 19 49: 5 50: 8 Sum = 4+2+25+8+1+12+23+19+5+8 = 107 Rows 51-60: 51: 1 52: 5 53: 1 54: 11 55: 23 56: 1 57: 18 58: 23 59: 7 60: 1 Sum = 1+5+1+11+23+1+18+23+7+1 = 91 Rows 61-70: 61: 1 62: 29 63: 7 64: 25 65: 8 66: 8 67: 11 68: 7 69: 1 70: 9 Sum = 1+29+7+25+8+8+11+7+1+9 = 106 Rows 71-80: 71: 1 72: 2 73: 1 74: 1 75: 6 76: 6 77: 7 78: 6 | G68: 9 | H68: 9.19 | I68: =ABS(G68-H68)/ABS(H68) -> 0.020674646 | J68: numerischer Referenzwert | K68: 1
A69: E1_A07 | B69: What is the average distance from home (DistanceFromHome)? Answer with the number only. | C69: gemini-3.6-flash | D69: 3 | E69: ok | F69: To find the average distance from home (`DistanceFromHome`) for the employees in this dataset, we sum the values in the `DistanceFromHome` column and divide by the total number of employees (rows). - **Total sum of `DistanceFromHome`**: 3,678 - **Total number of employees**: 400 - **Average**: 3,678 / 400 = 9.195 9.195 | G69: 9.195 | H69: 9.19 | I69: =ABS(G69-H69)/ABS(H69) -> 0.00054406964 | J69: numerischer Referenzwert | K69: 2
A70: E1_A07 | B70: What is the average distance from home (DistanceFromHome)? Answer with the number only. | C70: gemini-3.6-flash | D70: 4 | E70: ok | F70: To find the average distance from home (`DistanceFromHome`) for the provided dataset, we sum the `DistanceFromHome` values for all 500 employees and divide by the total number of employees (500). - **Sum:** 4,603 - **Count:** 500 - **Average:** 4,603 / 500 = 9.206 9.206 | G70: 9.206 | H70: 9.19 | I70: =ABS(G70-H70)/ABS(H70) -> 0.0017410229 | J70: numerischer Referenzwert | K70: 2
A71: E1_A07 | B71: What is the average distance from home (DistanceFromHome)? Answer with the number only. | C71: gemini-3.6-flash | D71: 5 | E71: ok | F71: 9.192517006802721 | G71: 9.192517 | H71: 9.19 | I71: =ABS(G71-H71)/ABS(H71) -> 0.0002738854 | J71: numerischer Referenzwert | K71: 2
A72: E1_A08 | B72: Which department (Department) has the highest attrition rate? Name the department. | C72: gpt-5.6-luna | D72: 1 | E72: ok | F72: Sales has the highest attrition rate. | H72: Sales: 0.2063; Human Resources: 0.1905; Research & Development: 0.1384 | I72: OK | J72: richtige Abteilung | K72: 2
A73: E1_A08 | B73: Which department (Department) has the highest attrition rate? Name the department. | C73: gpt-5.6-luna | D73: 2 | E73: ok | F73: **Sales** has the highest attrition rate. | H73: Sales: 0.2063; Human Resources: 0.1905; Research & Development: 0.1384 | I73: OK | J73: richtige Abteilung | K73: 2
A74: E1_A08 | B74: Which department (Department) has the highest attrition rate? Name the department. | C74: gpt-5.6-luna | D74: 3 | E74: ok | F74: Sales has the highest attrition rate. | H74: Sales: 0.2063; Human Resources: 0.1905; Research & Development: 0.1384 | I74: OK | J74: richtige Abteilung | K74: 2
A75: E1_A08 | B75: Which department (Department) has the highest attrition rate? Name the department. | C75: gpt-5.6-luna | D75: 4 | E75: ok | F75: Sales. | H75: Sales: 0.2063; Human Resources: 0.1905; Research & Development: 0.1384 | I75: OK | J75: richtige Abteilung | K75: 2
A76: E1_A08 | B76: Which department (Department) has the highest attrition rate? Name the department. | C76: gpt-5.6-luna | D76: 5 | E76: ok | F76: Sales. | H76: Sales: 0.2063; Human Resources: 0.1905; Research & Development: 0.1384 | I76: OK | J76: richtige Abteilung | K76: 2
A77: E1_A08 | B77: Which department (Department) has the highest attrition rate? Name the department. | C77: gemini-3.6-flash | D77: 1 | E77: ok | F77: To find the department with the highest attrition rate, we calculate the proportion of employees who left (`Attrition = Yes`) relative to the total number of employees in each department: 1. **Sales:** * Total Employees: 179 * Attrition Count (`Yes`): 37 * **Attrition Rate: ~20.67%** 2. **Human Resources:** * Total Employees: 27 * Attrition Count (`Yes`): 5 * **Attrition Rate: ~18.52%** 3. **Research & Development:** * Total Employees: 294 * Attrition Count (`Yes`): 41 * **Attrition Rate: ~13.95%** The department with the highest attrition rate is **Sales**. | H77: Sales: 0.2063; Human Resources: 0.1905; Research & Development: 0.1384 | I77: OK | J77: richtige Abteilung | K77: 2
A78: E1_A08 | B78: Which department (Department) has the highest attrition rate? Name the department. | C78: gemini-3.6-flash | D78: 2 | E78: ABGESCHNITTEN | F78: Human Resources... (No) Line 309: 50,No,Travel_Frequently,1246,Human Resources... (No) Line 310: 44,No,Travel_Rarely,1112,Human Resources... (No) Line 316: 42,No,Non-Travel,179,Human Resources... (No) Line 321: 38,No,Travel_Rarely,433,Human Resources... (No) Line 328: 33,No,Travel_Rarely,147,Human Resources... (No) Line 332: 34,No,Travel_Frequently,648,Human Resources... (No) Line 336: 35,No,Travel_Rarely,528,Human Resources... (No) Line 352: 42,No,Travel_Rarely,1147,Human Resources... (No) Line 353: 29,No,Travel_Rarely,332,Human Resources... (No) Line 358: 46,No,Travel_Rarely,991,Human Resour … | H78: Sales: 0.2063; Human Resources: 0.1905; Research & Development: 0.1384 | I78: ? | J78: richtige Abteilung | K78: 0
A79: E1_A08 | B79: Which department (Department) has the highest attrition rate? Name the department. | C79: gemini-3.6-flash | D79: 3 | E79: ok | F79: To determine which department has the highest attrition rate in this dataset (the IBM HR Employee Attrition dataset), we calculate the attrition rate for each department as: $$\text{Attrition Rate} = \frac{\text{Number of employees who left (Attrition = Yes)}}{\text{Total number of employees in the department}} \times 100\%$$ ### **Department Breakdown:** 1. **Sales:** * **Total Employees:** 446 * **Attrition (Yes):** 92 * **Attrition Rate:** $\approx \mathbf{20.63\%}$ 2. **Human Resources:** * **Total Employees:** 63 * **Attrition (Yes):** 12 * **Attrition Rate:** $\appro … | H79: Sales: 0.2063; Human Resources: 0.1905; Research & Development: 0.1384 | I79: OK | J79: richtige Abteilung | K79: 2
A80: E1_A08 | B80: Which department (Department) has the highest attrition rate? Name the department. | C80: gemini-3.6-flash | D80: 4 | E80: ok | F80: To determine the department with the highest attrition rate, we calculate the percentage of employees who left (`Attrition = "Yes"`) within each department: 1. **Human Resources (HR):** - Total Employees: 36 - Attrition ("Yes"): 9 - **Attrition Rate:** $9 / 36 = 25.0\%$ 2. **Sales:** - Total Employees: 138 - Attrition ("Yes"): 29 - **Attrition Rate:** $29 / 138 \approx 21.01\%$ 3. **Research & Development (R&D):** - Total Employees: 226 - Attrition ("Yes"): 27 - **Attrition Rate:** $27 / 226 \approx 11.95\%$ ### **Answer:** **Human Resources** | H80: Sales: 0.2063; Human Resources: 0.1905; Research & Development: 0.1384 | I80: Wrong | J80: richtige Abteilung | K80: 0
A81: E1_A08 | B81: Which department (Department) has the highest attrition rate? Name the department. | C81: gemini-3.6-flash | D81: 5 | E81: ok | F81: To determine which department has the highest attrition rate, we calculate the number of employees who left (`Attrition = Yes`) relative to the total number of employees in each department: 1. **Sales**: - Total Employees: 446 - Attritions (`Yes`): 92 - **Attrition Rate**: **~20.63%** 2. **Human Resources**: - Total Employees: 63 - Attritions (`Yes`): 12 - **Attrition Rate**: **~19.05%** 3. **Research & Development**: - Total Employees: 961 - Attritions (`Yes`): 133 - **Attrition Rate**: **~13.84%** ### Answer: The department with the highest attrition rate is ** … | H81: Sales: 0.2063; Human Resources: 0.1905; Research & Development: 0.1384 | I81: OK | J81: richtige Abteilung | K81: 2
A82: E1_A09 | B82: Do employees who work overtime (OverTime) have a higher or lower attrition rate than those who do not? State the direction. | C82: gpt-5.6-luna | D82: 1 | E82: ok | F82: Employees who work overtime have a **higher attrition rate** than employees who do not work overtime. | H82: Yes: 0.3053; No: 0.1044 | I82: OK | J82: "Yes" höher | K82: 2
A83: E1_A09 | B83: Do employees who work overtime (OverTime) have a higher or lower attrition rate than those who do not? State the direction. | C83: gpt-5.6-luna | D83: 2 | E83: ok | F83: Employees who work overtime have a **higher attrition rate** than those who do not work overtime. | H83: Yes: 0.3053; No: 0.1044 | I83: OK | J83: "Yes" höher | K83: 2
... A101: E1_A10 | B101: Which marital status (MaritalStatus) group has the highest attrition rate? Name the group. | C101: gemini-3.6-flash | D101: 5 | E101: ok | F101: To determine which marital status group (`MaritalStatus`) has the highest attrition rate, let's analyze the counts for each group in the provided dataset: --- ### **Attrition Breakdown by Marital Status:** 1. **Single:** * **Total Employees:** 146 * **Attrited (`Attrition = Yes`):** 37 * **Attrition Rate:** $\approx 25.34\%$ 2. **Married:** * **Total Employees:** 183 * **Attrited (`Attrition = Yes`):** 18 * **Attrition Rate:** $\approx 9.84\%$ 3. **Divorced:** * **Total Employees:** 111 * **Attrited (`Attrition = Yes`):** 7 * **Attrition Rate:** $\approx 6.31\%$ … | H101: Single: 0.2553; Married: 0.1248; Divorced: 0.1009 | I101: OK | J101: richtige Gruppe | K101: 2

Sheet Auswertung A
A1: Frage-ID | B1: gpt-5.6-luna | C1: gemini-3.6-flash | D1: Luna SD | E1: Gemini SD
A2: E1_A01 | B2: =AVERAGEIFS('A faktisch'!$K:$K,'A faktisch'!$A:$A,$A2,'A faktisch'!$C:$C,B$1) -> 2 | C2: =AVERAGEIFS('A faktisch'!$K:$K,'A faktisch'!$A:$A,$A2,'A faktisch'!$C:$C,C$1) -> 0.4 | D2: =IFERROR(__xludf.DUMMYFUNCTION("STDEV.S(FILTER('A faktisch'!$K:$K,'A faktisch'!$A:$A=$A2,'A faktisch'!$C:$C=""gpt-5.6-luna""))"),0.0) -> 0 | E2: =IFERROR(__xludf.DUMMYFUNCTION("STDEV.S(FILTER('A faktisch'!$K:$K,'A faktisch'!$A:$A=$A2,'A faktisch'!$C:$C=""gemini-3.6-flash""))"),0.8944271909999159) -> 0.89442719
A3: E1_A02 | B3: =AVERAGEIFS('A faktisch'!$K:$K,'A faktisch'!$A:$A,$A3,'A faktisch'!$C:$C,B$1) -> 2 | C3: =AVERAGEIFS('A faktisch'!$K:$K,'A faktisch'!$A:$A,$A3,'A faktisch'!$C:$C,C$1) -> 2 | D3: =IFERROR(__xludf.DUMMYFUNCTION("STDEV.S(FILTER('A faktisch'!$K:$K,'A faktisch'!$A:$A=$A3,'A faktisch'!$C:$C=""gpt-5.6-luna""))"),0.0) -> 0 | E3: =IFERROR(__xludf.DUMMYFUNCTION("STDEV.S(FILTER('A faktisch'!$K:$K,'A faktisch'!$A:$A=$A3,'A faktisch'!$C:$C=""gemini-3.6-flash""))"),0.0) -> 0
A4: E1_A03 | B4: =AVERAGEIFS('A faktisch'!$K:$K,'A faktisch'!$A:$A,$A4,'A faktisch'!$C:$C,B$1) -> 2 | C4: =AVERAGEIFS('A faktisch'!$K:$K,'A faktisch'!$A:$A,$A4,'A faktisch'!$C:$C,C$1) -> 1.6 | D4: =IFERROR(__xludf.DUMMYFUNCTION("STDEV.S(FILTER('A faktisch'!$K:$K,'A faktisch'!$A:$A=$A4,'A faktisch'!$C:$C=""gpt-5.6-luna""))"),0.0) -> 0 | E4: =IFERROR(__xludf.DUMMYFUNCTION("STDEV.S(FILTER('A faktisch'!$K:$K,'A faktisch'!$A:$A=$A4,'A faktisch'!$C:$C=""gemini-3.6-flash""))"),0.8944271909999159) -> 0.89442719
A5: E1_A04 | B5: =AVERAGEIFS('A faktisch'!$K:$K,'A faktisch'!$A:$A,$A5,'A faktisch'!$C:$C,B$1) -> 2 | C5: =AVERAGEIFS('A faktisch'!$K:$K,'A faktisch'!$A:$A,$A5,'A faktisch'!$C:$C,C$1) -> 0.8 | D5: =IFERROR(__xludf.DUMMYFUNCTION("STDEV.S(FILTER('A faktisch'!$K:$K,'A faktisch'!$A:$A=$A5,'A faktisch'!$C:$C=""gpt-5.6-luna""))"),0.0) -> 0 | E5: =IFERROR(__xludf.DUMMYFUNCTION("STDEV.S(FILTER('A faktisch'!$K:$K,'A faktisch'!$A:$A=$A5,'A faktisch'!$C:$C=""gemini-3.6-flash""))"),0.4472135954999579) -> 0.4472136
A6: E1_A05 | B6: =AVERAGEIFS('A faktisch'!$K:$K,'A faktisch'!$A:$A,$A6,'A faktisch'!$C:$C,B$1) -> 2 | C6: =AVERAGEIFS('A faktisch'!$K:$K,'A faktisch'!$A:$A,$A6,'A faktisch'!$C:$C,C$1) -> 2 | D6: =IFERROR(__xludf.DUMMYFUNCTION("STDEV.S(FILTER('A faktisch'!$K:$K,'A faktisch'!$A:$A=$A6,'A faktisch'!$C:$C=""gpt-5.6-luna""))"),0.0) -> 0 | E6: =IFERROR(__xludf.DUMMYFUNCTION("STDEV.S(FILTER('A faktisch'!$K:$K,'A faktisch'!$A:$A=$A6,'A faktisch'!$C:$C=""gemini-3.6-flash""))"),0.0) -> 0
A7: E1_A06 | B7: =AVERAGEIFS('A faktisch'!$K:$K,'A faktisch'!$A:$A,$A7,'A faktisch'!$C:$C,B$1) -> 1.6 | C7: =AVERAGEIFS('A faktisch'!$K:$K,'A faktisch'!$A:$A,$A7,'A faktisch'!$C:$C,C$1) -> 0 | D7: =IFERROR(__xludf.DUMMYFUNCTION("STDEV.S(FILTER('A faktisch'!$K:$K,'A faktisch'!$A:$A=$A7,'A faktisch'!$C:$C=""gpt-5.6-luna""))"),0.8944271909999159) -> 0.89442719 | E7: =IFERROR(__xludf.DUMMYFUNCTION("STDEV.S(FILTER('A faktisch'!$K:$K,'A faktisch'!$A:$A=$A7,'A faktisch'!$C:$C=""gemini-3.6-flash""))"),0.0) -> 0
A8: E1_A07 | B8: =AVERAGEIFS('A faktisch'!$K:$K,'A faktisch'!$A:$A,$A8,'A faktisch'!$C:$C,B$1) -> 2 | C8: =AVERAGEIFS('A faktisch'!$K:$K,'A faktisch'!$A:$A,$A8,'A faktisch'!$C:$C,C$1) -> 1.8 | D8: =IFERROR(__xludf.DUMMYFUNCTION("STDEV.S(FILTER('A faktisch'!$K:$K,'A faktisch'!$A:$A=$A8,'A faktisch'!$C:$C=""gpt-5.6-luna""))"),0.0) -> 0 | E8: =IFERROR(__xludf.DUMMYFUNCTION("STDEV.S(FILTER('A faktisch'!$K:$K,'A faktisch'!$A:$A=$A8,'A faktisch'!$C:$C=""gemini-3.6-flash""))"),0.4472135954999579) -> 0.4472136
A9: E1_A08 | B9: =AVERAGEIFS('A faktisch'!$K:$K,'A faktisch'!$A:$A,$A9,'A faktisch'!$C:$C,B$1) -> 2 | C9: =AVERAGEIFS('A faktisch'!$K:$K,'A faktisch'!$A:$A,$A9,'A faktisch'!$C:$C,C$1) -> 1.2 | D9: =IFERROR(__xludf.DUMMYFUNCTION("STDEV.S(FILTER('A faktisch'!$K:$K,'A faktisch'!$A:$A=$A9,'A faktisch'!$C:$C=""gpt-5.6-luna""))"),0.0) -> 0 | E9: =IFERROR(__xludf.DUMMYFUNCTION("STDEV.S(FILTER('A faktisch'!$K:$K,'A faktisch'!$A:$A=$A9,'A faktisch'!$C:$C=""gemini-3.6-flash""))"),1.0954451150103321) -> 1.0954451
A10: E1_A09 | B10: =AVERAGEIFS('A faktisch'!$K:$K,'A faktisch'!$A:$A,$A10,'A faktisch'!$C:$C,B$1) -> 2 | C10: =AVERAGEIFS('A faktisch'!$K:$K,'A faktisch'!$A:$A,$A10,'A faktisch'!$C:$C,C$1) -> 2 | D10: =IFERROR(__xludf.DUMMYFUNCTION("STDEV.S(FILTER('A faktisch'!$K:$K,'A faktisch'!$A:$A=$A10,'A faktisch'!$C:$C=""gpt-5.6-luna""))"),0.0) -> 0 | E10: =IFERROR(__xludf.DUMMYFUNCTION("STDEV.S(FILTER('A faktisch'!$K:$K,'A faktisch'!$A:$A=$A10,'A faktisch'!$C:$C=""gemini-3.6-flash""))"),0.0) -> 0
A11: E1_A10 | B11: =AVERAGEIFS('A faktisch'!$K:$K,'A faktisch'!$A:$A,$A11,'A faktisch'!$C:$C,B$1) -> 2 | C11: =AVERAGEIFS('A faktisch'!$K:$K,'A faktisch'!$A:$A,$A11,'A faktisch'!$C:$C,C$1) -> 2 | D11: 0 | E11: 0
A12: Gesamtmittelwert | B12: =AVERAGE(B2:B11) -> 1.96 | C12: =AVERAGE(C2:C11) -> 1.38 | D12: 0 | E12: 0

Sheet B interpretativ
A1: Frage-ID | B1: Frage | C1: Modell | D1: It. | E1: Status | F1: Antwort | G1: Referenz (Soll-Inhalt) | H1: Punkte 0-2 | I1: Notiz
A2: E1_B01 | B2: Which factors are most strongly associated with employees leaving the company (Attrition)? Name the most important ones and support your answer with concrete values from the data. | C2: gemini-3.6-flash | D2: 1 | E2: ok | F2: Based on an analysis of the provided dataset, the most significant factors strongly associated with employee attrition (**Attrition = Yes**) are:\n\n---\n\n### 1. **OverTime**\n* **Finding:** Working overtime is one of the single strongest predictors of employee departure.\n* **Evidence from Data:** \n * A disproportionately large percentage of employees who left the company worked overtime (`OverTime = Yes`).\n * Examples of employees leaving with `OverTime = Yes`: EmployeeNumber 1 (Age 41), EmployeeNumber 4 (Age 37), EmployeeNumber 19 (Age 28), EmployeeNumber 64 (Age 48), EmployeeNumber 65 (Age 28), EmployeeNumber 137 (Age 20), EmployeeNumber 142 (Age 25), EmployeeNumber 147 (Age 34), and many others.\n * Employees who do not work overtime (`OverTime = No`) stay with the company at a significantly higher rate.\n\n---\n\n### 2. **Marital Status & Age**\n* **Finding:** Younger and single employees are significantly more likely to leave.\n* **Evidence from Data:**\n * **Single Employees:** Single employees represent a major portion of all attrition cases (e.g., EmployeeNumbers 1, 4, 19, 27, 31, 33, 55, 64, 65, 137, 142, 147, 167, 235, 243, etc.).\n * **Younger Age:** Many departures occur among employees aged under 30 (e.g., ages 18, 19, 20, 21, 24, 25, 26, 28, 29). For instance:\n * EmployeeNumber 167 (Age 19, Single, Attrition = Yes)\n * EmployeeNumber 235 (Age 19, Single, Attrition = Yes)\n * EmployeeNumber 243 (Age 19, Single, Attrition = Yes)\n * EmployeeNumber 137 (Age 20, Single, Attrition = Yes)\n\n---\n\n### 3. **Stock Option Level**\n* **Finding:** Employees with no stock options (`StockOptionLevel = 0`) are far more likely to leave compared to those with equity incentives (levels 1–3).\n* **Evidence from Data:**\n * Overwhelmingly, employees with `Attrition = Yes` have `StockOptionLevel = 0` (e.g., EmployeeNumbers 1, 4, 19, 27, 31, 33, 47, 55, 64, 65, 137, 142, 147, 167, 175, 179, etc.).\n * Having at least `StockOptionLevel = 1` or `2` serves as a strong retention mechanism.\n\n---\n\n### 4. **Business Travel Frequency**\n* **Finding:** Frequent travel correlates with higher turnover rates.\n* **Evidence from Data:**\n * While `Travel_Rarely` is the majority travel type overall, employees categorized as `Travel_Frequently` have a much higher rate of attrition relative to their total headcount.\n * Examples of frequent travelers who left include EmployeeNumbers 33 (Age 32), 137 (Age 20), 147 (Age 34), 179 (Age 51), 235 (Age 19), 299 (Age 30), 342 (Age 37), and 355 (Age 31).\n\n---\n\n### 5. **Job Level & Monthly Income**\n* **Finding:** Entry-level position holders (Job Level 1) with lower monthly compensation exhibit higher turnover.\n* **Evidence from Data:**\n * The vast majority of attrition cases occur at **JobLevel = 1** or **2** with lower `MonthlyIncome` (e.g., $1,009 to $3,500/month).\n * Examples:\n * EmployeeNumber 167: Monthly Income $1,675 (Level 1, Attrition = Yes)\n * EmployeeNumber 235: Monthly Income $2,325 (Level 1, Attrition = Yes)\n * EmployeeNumber 243: Monthly Income $1,102 (Level 1, Attrition = Yes)\n * EmployeeNumber 19: Monthly Income $2,028 (Level 1, Attrition = Yes)\n\n---\n\n### **Summary Risk Profile of a Departing Employee**\nAn employee with the highest likelihood of leaving typically matches this profile:\n* **Works OverTime:** Yes\n* **Marital Status:** Single\n* **Stock Option Level:** 0\n* **Age:** Under 30\n* **Job Level / Income:** Level 1, low monthly income | G2: {"wert": {"OverTime_num": 0.2461, "TotalWorkingYears": -0.1711, "JobLevel": -0.1691, "YearsInCurrentRole": -0.1605, "MonthlyIncome": -0.1598}, "typ": "rangfolge", "toleranz": "richtung", "quelle": "Pearson corr mit Attrition_num, Top 5 nach Betrag"} | H2: 1 | I2: Grundrichtung plausibel aber statt der stärksten Zusammenhänge werden u.a. MartialStatus, StockoptionLevel und Business Travel hervorgehoben
A3: E1_B01 | B3: Which factors are most strongly associated with employees leaving the company (Attrition)? Name the most important ones and support your answer with concrete values from the data. | C3: gemini-3.6-flash | D3: 2 | E3: ABGESCHNITTEN | F3: Based on an exploratory data analysis of the provided dataset, the following key factors are most strongly associated with employee attrition (**`Attrition = Yes`**):\n\n---\n\n### 1. OverTime Work (Strongest Single Predictor)\n* **Finding:** Working overtime is heavily linked to higher employee turnover.\n* **Data Evidence:**\n * Employees who work overtime (**`OverTime = Yes`**) have an attrition rate of approximately **30–32%**, compared to only **~10–11%** for those who do not work overtime (**`OverTime = No`**).\n * Out of all employees who left the company, **nearly half worked overtime**, even though overtime workers represent a much smaller minority of the overall workforce.\n\n---\n\n### 2. Age and Total Working Years (Younger / Early-Career Employees)\n* **Finding:** Younger employees and those early in their careers are significantly more likely to leave.\n* **Data Evidence:**\n * Employees **under 30 years old** experience an attrition rate of nearly **25–30%**, whereas employees **over 40 years old** have an attrition rate below **10%**.\n * Among very young employees (ages 18–22), attrition is particularly severe (e.g., Employee Nos. 167, 235, 243, 405, 478, 701, 922, 1156, 1279, 1624 all left).\n * **TotalWorkingYears:** Employees leaving the company have a much lower average total working years (around **4–6 years**) compared to those staying (around **11+ years**).\n\n---\n\n### 3. Stock Option Level\n* **Finding:** Lack of stock options significantly increases turnover risk.\n* **Data Evidence:**\n * Employees with **`StockOptionLevel = 0`** account for over **60% of all attritions**.\n * Employees with **`StockOptionLevel = 1` or `2`** show significantly lower attrition rates (~7–10%), indicating that equity grants serve as an effective retention mechanism.\n\n---\n\n### 4. Monthly Income & Job Level\n* **Finding:** Lower job levels and lower monthly salaries correlate strongly with higher attrition.\n* **Data Evidence:**\n * **Job Level 1** employees (entry-level) have the highest attrition rate.\n * Employees who left had a median Monthly Income around **$2,500 – $3,500**, whereas retained employees had a median Monthly Income well above **$5,000**.\n * Senior roles like **Manager** and **Research Director** (Job Levels 4 & 5 with monthly incomes > $12,000) show near-zero attrition in this sample.\n\n---\n\n### 5. Business Travel Frequency\n* **Finding:** Frequent business travel drives higher turnover.\n* **Data Evidence:**\n * Employees in the **`Travel_Frequently`** category have an attrition rate of **~24%**, compared to **~13%** for **`Travel_Rarely`** and **~8%** for **`Non-Travel`**.\n\n---\n\n### 6. Job Role Disparities\n* **Finding:** Attrition is heavily concentrated in specific operational and frontline sales roles.\n* **Data Evidence:**\n * Roles with the highest attrition count and rate:\n 1. **Sales Representative** (high turnover due to lower base income and high travel)\n 2. **Laboratory Technician**\n 3. **Research Scientist**\n * In contrast, **Healthcare Representatives**, **Manufacturing Directors**, and **Managers** show very low attrition.\n\n---\n\n### Summary Checklist for Attrition Risk Profile\nAn employee at the **highest risk of leaving** typically matches this profile | G3: {"wert": {"OverTime_num": 0.2461, "TotalWorkingYears": -0.1711, "JobLevel": -0.1691, "YearsInCurrentRole": -0.1605, "MonthlyIncome": -0.1598}, "typ": "rangfolge", "toleranz": "richtung", "quelle": "Pearson corr mit Attrition_num, Top 5 nach Betrag"} | H3: 2 | I3: Zentrale Zusammenhänge korrekt identifiziert und überwiegend quantitativ belegt; einzelne kausale Formulierungen zu stark
A4: E1_B01 | B4: Which factors are most strongly associated with employees leaving the company (Attrition)? Name the most important ones and support your answer with concrete values from the data. | C4: gemini-3.6-flash | D4: 3 | E4: ok | F4: Based on an exploratory analysis of the provided dataset, the most important factors strongly associated with employee **Attrition ("Yes")** are: --- ### 1. **OverTime (Workload and Burnout)** * **Observation:** Working overtime is one of the single strongest predictors of employee departure. * **Data Evidence:** * A very large proportion of employees who left the company worked overtime (e.g., Employee #1, #4, #19, #33, #64, #65, #137, #142, #147, #161, #163). * Employees without overtime show significantly lower attrition rates and higher overall retention across almost all job roles and departments. --- ### 2. **Low Monthly Income and Entry Job Level (JobLevel = 1)** * **Observation:** Attrition is heavily concentrated among lower-earning employees and entry-level staff (Job Lev … | G4: {"wert": {"OverTime_num": 0.2461, "TotalWorkingYears": -0.1711, "JobLevel": -0.1691, "YearsInCurrentRole": -0.1605, "MonthlyIncome": -0.1598}, "typ": "rangfolge", "toleranz": "richtung", "quelle": "Pearson corr mit Attrition_num, Top 5 nach Betrag"} | H4: 1 | I4: Relevante Faktoren erkannt, aber überwiegend Einzelbeispiele statt aggregierter Evidenz und teilweise kausale Interpretation.
A5: E1_B01 | B5: Which factors are most strongly associated with employees leaving the company (Attrition)? Name the most important ones and support your answer with concrete values from the data. | C5: gemini-3.6-flash | D5: 4 | E5: ok | F5: Based on an exploratory data analysis of the provided dataset, the most critical factors strongly associated with employee **Attrition ("Yes")** are **OverTime**, **Monthly Income & Job Level**, **Age & Total Working Years**, **Stock Option Level & Marital Status**, and **Tenure with Company/Manager**. --- ### 1. OverTime Work (Workload Stress) * **Finding**: Working overtime is the single strongest indicator of employee attrition in this dataset. * **Data Evidence**: * A majority of employees who left the company (`Attrition = Yes`) were working overtime (`OverTime = Yes`). * Examples from the data: * Employee #1 (Age 41, Sales Executive): **OverTime = Yes** $\rightarrow$ Attrition = **Yes** * Employee #4 (Age 37, Lab Technician, Income $2,090): **OverTime = Yes** $\rightar … | G5: {"wert": {"OverTime_num": 0.2461, "TotalWorkingYears": -0.1711, "JobLevel": -0.1691, "YearsInCurrentRole": -0.1605, "MonthlyIncome": -0.1598}, "typ": "rangfolge", "toleranz": "richtung", "quelle": "Pearson corr mit Attrition_num, Top 5 nach Betrag"} | H5: 1 | I5: Relevante Faktoren erkannt, aber überwiegend Einzelbeispiele; zusätzlich unbelegte kausale Erklärung bei Marital Status („due to ... higher mobility“).
A6: E1_B01 | B6: Which factors are most strongly associated with employees leaving the company (Attrition)? Name the most important ones and support your answer with concrete values from the data. | C6: gemini-3.6-flash | D6: 5 | E6: ok | F6: Based on an exploratory data analysis of the provided dataset (500 employee records, with an overall attrition rate of **15.8%** / 79 left vs. 421 stayed), the following factors are most strongly associated with employee attrition: --- ### 1. OverTime (Work Overtime) **OverTime is the single strongest binary predictor of attrition.** * **OverTime = Yes:** **29.1%** attrition rate (41 out of 141 employees working overtime left). * **OverTime = No:** **10.6%** attrition rate (38 out of 359 employees not working overtime left). * **Key Finding:** Employees who work overtime are nearly **2.75x more likely** to leave the company. --- ### 2. Monthly Income & Job Level **Lower compensation and entry-level positions show significantly higher attrition.** * **Average Monthly Income:** * **Att … | G6: {"wert": {"OverTime_num": 0.2461, "TotalWorkingYears": -0.1711, "JobLevel": -0.1691, "YearsInCurrentRole": -0.1605, "MonthlyIncome": -0.1598}, "typ": "rangfolge", "toleranz": "richtung", "quelle": "Pearson corr mit Attrition_num, Top 5 nach Betrag"} | H6: 0 | I6: Analyse basiert fälschlicherweise auf 500 statt 1.470 Beobachtungen; dadurch stammen die konkreten Kennzahlen nicht aus dem vollständigen Datensatz.
A7: E1_B01 | C7: gpt-5.6-luna | D7: 1 | E7: ok | F7: The strongest associations with **Attrition = Yes** in this dataset are: | Factor | Evidence from the data | |---|---| | **Overtime** | Employees working overtime leave at about **30.5%** (**127 of 416**) versus about **10.4%** (**110 of 1,054**) among employees not working overtime. This is the clearest association—roughly a threefold difference. | | **Stock-option level** | Attrition is highest for employees with **StockOptionLevel = 0**: about **24.4%** (**154 of 631**). It is much lower for level 1, about **9.4%** (**56 of 596**), and level 2, about **7.6%** (**12 of 158**). | | **Job level / seniority and compensation** | **JobLevel = 1** employees have attrition of roughly **26%** (**143 of 543**), compared with approximately **10%** at JobLevel 2 and below **5%** at JobLevel 4. The … | G7: {"wert": {"OverTime_num": 0.2461, "TotalWorkingYears": -0.1711, "JobLevel": -0.1691, "YearsInCurrentRole": -0.1605, "MonthlyIncome": -0.1598}, "typ": "rangfolge", "toleranz": "richtung", "quelle": "Pearson corr mit Attrition_num, Top 5 nach Betrag"} | H7: 2
A8: E1_B01 | B8: Which factors are most strongly associated with employees leaving the company (Attrition)? Name the most important ones and support your answer with concrete values from the data. | C8: gpt-5.6-luna | D8: 2 | E8: ok | F8: The strongest associations with attrition in this dataset are: | Factor | Attrition pattern | |---|---| | **Overtime** | Employees working overtime: **127 of 416 left (30.5%)**. Employees not working overtime: **110 of 1,054 (10.4%)**. This is the clearest categorical difference—nearly **3× higher** attrition with overtime. | | **Job level / seniority** | Attrition is concentrated among lower job levels. **Job Level 1:** **143 of 543 (26.3%)** left; **Job Level 2:** **52 of 534 (9.7%)**; **Job Level 4:** **5 of 106 (4.7%)**. Lower-level employees therefore have substantially higher turnover. | | **Stock-option level** | Employees with no stock options had attrition of **154 of 631 (24.4%)**. This fell to **56 of 596 (9.4%)** for stock-option level 1 and **12 of 158 (7.6%)** for level 2. L … | G8: {"wert": {"OverTime_num": 0.2461, "TotalWorkingYears": -0.1711, "JobLevel": -0.1691, "YearsInCurrentRole": -0.1605, "MonthlyIncome": -0.1598}, "typ": "rangfolge", "toleranz": "richtung", "quelle": "Pearson corr mit Attrition_num, Top 5 nach Betrag"} | H8: 2
A9: E1_B01 | B9: Which factors are most strongly associated with employees leaving the company (Attrition)? Name the most important ones and support your answer with concrete values from the data. | C9: gpt-5.6-luna | D9: 3 | E9: ok | F9: Using the overall attrition rate as a baseline: - **237 of 1,470 employees left: 16.1%** The strongest associations in this dataset are: | Factor | Group | Attrition | Attrition rate | |---|---:|---:|---:| | **OverTime** | Yes | 127 / 416 | **30.5%** | | | No | 110 / 1,054 | 10.4% | | **Job level** | Level 1 | 143 / 543 | **26.3%** | | | Level 2 | 52 / 534 | 9.7% | | | Level 4 | 5 / 106 | 4.7% | | **Marital status** | Single | 120 / 470 | **25.5%** | | | Married | 84 / 673 | 12.5% | | | Divorced | 33 / 327 | 10.1% | | **Business travel** | Travel_Frequently | 69 / 277 | **24.9%** | | | Travel_Rarely | 156 / 1,043 | 15.0% | | | Non-Travel | 12 / 150 | 8.0% | | **Stock option level** | 0 | 154 / 631 | **24.4%** | | | 1 | 56 / 596 | 9.4% | | | 2 | 12 / 158 | 7.6% | | **Job role** … | G9: {"wert": {"OverTime_num": 0.2461, "TotalWorkingYears": -0.1711, "JobLevel": -0.1691, "YearsInCurrentRole": -0.1605, "MonthlyIncome": -0.1598}, "typ": "rangfolge", "toleranz": "richtung", "quelle": "Pearson corr mit Attrition_num, Top 5 nach Betrag"} | H9: 2
A10: E1_B01 | B10: Which factors are most strongly associated with employees leaving the company (Attrition)? Name the most important ones and support your answer with concrete values from the data. | C10: gpt-5.6-luna | D10: 4 | E10: ok | F10: The strongest associations with attrition are behavioral and job-related rather than demographic. The clearest patterns are: | Factor | Evidence from the data | |---|---| | **OverTime** | Employees working overtime leave at a much higher rate: **127 of 416 overtime employees (30.5%)** left, compared with **110 of 1,054 non-overtime employees (10.4%)**. This is the strongest single categorical relationship. | | **Job level / seniority** | Attrition is concentrated among junior employees: **143 of 543 Job Level 1 employees (26.3%)** left, versus **52 of 534 at Level 2 (9.7%)**, **32 of 218 at Level 3 (14.7%)**, and only **5 of 106 at Level 4 (4.7%)**. | | **Age and experience** | Younger and newer employees are more likely to leave. The data includes multiple very young leavers—for example, … | G10: {"wert": {"OverTime_num": 0.2461, "TotalWorkingYears": -0.1711, "JobLevel": -0.1691, "YearsInCurrentRole": -0.1605, "MonthlyIncome": -0.1598}, "typ": "rangfolge", "toleranz": "richtung", "quelle": "Pearson corr mit Attrition_num, Top 5 nach Betrag"} | H10: 2 | I10: Teilweise Überinterpretation (z. B. „Stock options likely represent a retention incentive“, „Longer commutes are associated with higher attrition“ ohne starke quantitative Belege).
A11: E1_B01 | B11: Which factors are most strongly associated with employees leaving the company (Attrition)? Name the most important ones and support your answer with concrete values from the data. | C11: gpt-5.6-luna | D11: 5 | E11: ok | F11: The dataset contains **1,470 employees**, of whom **237 left** (**16.1% overall attrition**). The strongest associations with attrition are: | Factor | Attrition pattern | Interpretation | |---|---:|---| | **OverTime** | **127 of 416 employees working overtime left (30.5%)**, versus **110 of 1,054 not working overtime (10.4%)** | Overtime employees were about **2.9 times as likely** to leave. This is the clearest categorical association. | | **Age / career stage** | Employees who left had mean age **33.6**, compared with **37.6** among those who stayed | Attrition is concentrated among younger employees, particularly early-career staff. | | **Job level and income** | Mean JobLevel was **1.64** for leavers versus **2.07** for non-leavers; mean MonthlyIncome was approximately **$4,787** ver … | G11: {"wert": {"OverTime_num": 0.2461, "TotalWorkingYears": -0.1711, "JobLevel": -0.1691, "YearsInCurrentRole": -0.1605, "MonthlyIncome": -0.1598}, "typ": "rangfolge", "toleranz": "richtung", "quelle": "Pearson corr mit Attrition_num, Top 5 nach Betrag"} | H11: 2
A12: E1_B02 | B12: Are there combinations of characteristics that occur together with a particularly high attrition rate? Describe the most notable combinations. | C12: gemini-3.6-flash | D12: 1 | E12: ok | F12: Based on an exploratory analysis of this HR dataset, several specific combinations of employee characteristics correlate with a **significantly higher rate of attrition**: --- ### 1. **OverTime = "Yes" + Low Job Level (Job Level 1) / Specific Roles** * **Notable Roles:** *Sales Representative* and *Laboratory Technician* * **Pattern:** Employees in entry-level positions (Job Level 1) who work **OverTime** exhibit the highest overall attrition rates in the dataset. * **Key Driver:** The combination of lower base pay, high workload/overtime demand, and lower job autonomy creates severe burnout and turnover risk. --- ### 2. **Marital Status = "Single" + OverTime = "Yes"** * **Pattern:** Single employees who work OverTime leave at a rate substantially higher than married or divorced emplo … | G12: {"wert": [{"wenn": ["OverTime_Yes", "YearsAtCompany_bin_niedrig"], "dann": "Attrition_Yes", "support": 0.051, "confidence": 0.431, "improvement": 0.1257, "lift": 2.6735}, {"wenn": ["Age_bin_niedrig", "MaritalStatus_Single"], "dann": "Attrition_Yes", "support": 0.051, "confidence": 0.3886, "improvement": 0.1333, "lift": 2.4103}, {"wenn": ["Age_bin_niedrig", "YearsAtCompany_bin_niedrig"], "dann": "A | H12: 1 | I12: zentrale Referenzkombination OverTime + niedrige Betriebszugehörigkeit nicht klar erkannt.
A13: E1_B02 | B13: Are there combinations of characteristics that occur together with a particularly high attrition rate? Describe the most notable combinations. | C13: gemini-3.6-flash | D13: 2 | E13: ok | F13: Based on exploratory data analysis of this dataset (IBM HR Analytics dataset), several distinct **combinations of characteristics** exhibit a particularly high rate of employee attrition (`Attrition = Yes`). The most notable high-attrition combinations include: --- ### 1. **OverTime = "Yes" + MaritalStatus = "Single"** * **Key Traits:** Employees working overtime who are single. * **Analysis:** Overtime is one of the strongest individual predictors of attrition. When combined with a single marital status, employees have fewer personal ties binding them to a location/schedule and greater mobility, leading to a significantly higher turnover rate compared to married or divorced peers working standard hours. --- ### 2. **JobLevel = 1 (Entry-Level) + OverTime = "Yes" + Low Tenure (`YearsA … | G13: {"wert": [{"wenn": ["OverTime_Yes", "YearsAtCompany_bin_niedrig"], "dann": "Attrition_Yes", "support": 0.051, "confidence": 0.431, "improvement": 0.1257, "lift": 2.6735}, {"wenn": ["Age_bin_niedrig", "MaritalStatus_Single"], "dann": "Attrition_Yes", "support": 0.051, "confidence": 0.3886, "improvement": 0.1333, "lift": 2.4103}, {"wenn": ["Age_bin_niedrig", "YearsAtCompany_bin_niedrig"], "dann": "A | H13: 1 | I13: Starke unbelegte Kausalerklärungen („golden handcuffs“, income volatility, lifestyle fatigue); mehrere Kombinationen weichen deutlich von den stärksten Referenzregeln ab.
A14: E1_B02 | B14: Are there combinations of characteristics that occur together with a particularly high attrition rate? Describe the most notable combinations. | C14: gemini-3.6-flash | D14: 3 | E14: ok | F14: Based on an exploratory data analysis of the provided HR dataset, several key combinations of characteristics are associated with a **significantly higher attrition rate** compared to the overall company baseline (which is roughly 16%): --- ### 1. **OverTime = "Yes" + MaritalStatus = "Single"** * **Why it occurs:** Single employees generally have higher personal mobility and fewer family ties holding them to a specific job. When combined with the strain of frequent overtime, burnout leads to a very high rate of departure (often exceeding 35–40% attrition within this subgroup). * **Key Driver:** High workload strain coupled with high career mobility. --- ### 2. **OverTime = "Yes" + JobLevel = 1** * **Why it occurs:** Entry-level employees (Job Level 1, such as *Research Scientists*, *La … | G14: {"wert": [{"wenn": ["OverTime_Yes", "YearsAtCompany_bin_niedrig"], "dann": "Attrition_Yes", "support": 0.051, "confidence": 0.431, "improvement": 0.1257, "lift": 2.6735}, {"wenn": ["Age_bin_niedrig", "MaritalStatus_Single"], "dann": "Attrition_Yes", "support": 0.051, "confidence": 0.3886, "improvement": 0.1333, "lift": 2.4103}, {"wenn": ["Age_bin_niedrig", "YearsAtCompany_bin_niedrig"], "dann": "A | H14: 1 | I14: Erfundene Ursachen wie Burnout, „financial retention hooks“ und höhere Jobwechselbereitschaft; konkrete behauptete Attrition-Rate von 35–40 % für Single + OverTime wird nicht durch die angegebene Referenzregel belegt
A15: E1_B02 | B15: Are there combinations of characteristics that occur together with a particularly high attrition rate? Describe the most notable combinations. | C15: gemini-3.6-flash | D15: 4 | E15: ok | F15: Based on an analysis of the provided dataset, several distinct **combinations of characteristics** are associated with significantly higher attrition rates compared to the dataset average. The most notable high-attrition combinations include: --- ### 1. OverTime ("Yes") + Single Marital Status + No Stock Options (`StockOptionLevel = 0`) * **Description:** Employees who work overtime, are single, and do not hold stock options exhibit one of the highest attrition rates in the dataset. * **Key Observations:** * Single employees have higher job mobility and fewer ties holding them to the organization. * When combined with required overtime and a lack of long-term financial incentives (stock options = 0), turnover increases dramatically across various departments and age groups. --- # … | G15: {"wert": [{"wenn": ["OverTime_Yes", "YearsAtCompany_bin_niedrig"], "dann": "Attrition_Yes", "support": 0.051, "confidence": 0.431, "improvement": 0.1257, "lift": 2.6735}, {"wenn": ["Age_bin_niedrig", "MaritalStatus_Single"], "dann": "Attrition_Yes", "support": 0.051, "confidence": 0.3886, "improvement": 0.1333, "lift": 2.4103}, {"wenn": ["Age_bin_niedrig", "YearsAtCompany_bin_niedrig"], "dann": "A | H15: 1 | I15: Überwiegend qualitative Behauptungen ohne Kennzahlen; Aussagen wie „attrition is almost immediate“ bei JobInvolvement=1 + OverTime sind deutlich überzogen und nicht durch die Referenzregeln gestützt
A16: E1_B02 | B16: Are there combinations of characteristics that occur together with a particularly high attrition rate? Describe the most notable combinations. | C16: gemini-3.6-flash | D16: 5 | E16: ok | F16: Based on an analysis of the provided dataset, several distinct combinations of employee characteristics are strongly associated with high attrition rates. The most notable combinations include: --- ### 1. **Working Overtime + Single Marital Status + Low Stock Option Level (Level 0)** * **Characteristics:** `OverTime = Yes`, `MaritalStatus = Single`, `StockOptionLevel = 0` * **Insight:** Employees who regularly work overtime, have no stock options, and are single exhibit one of the highest attrition rates in the dataset. The lack of financial/equity retention incentives combined with high workload and fewer personal ties/dependents makes this group particularly mobile and prone to leaving. --- ### 2. **Sales Representatives + Frequent Travel / Overtime** * **Characteristics:** `JobRole … | G16: {"wert": [{"wenn": ["OverTime_Yes", "YearsAtCompany_bin_niedrig"], "dann": "Attrition_Yes", "support": 0.051, "confidence": 0.431, "improvement": 0.1257, "lift": 2.6735}, {"wenn": ["Age_bin_niedrig", "MaritalStatus_Single"], "dann": "Attrition_Yes", "support": 0.051, "confidence": 0.3886, "improvement": 0.1333, "lift": 2.4103}, {"wenn": ["Age_bin_niedrig", "YearsAtCompany_bin_niedrig"], "dann": "A | H16: 1 | I16: Mehrere plausible Faktoren, aber starke unbelegte Ursachenbehauptungen („travel burnout“, „aggressive targets“, „low switching costs“); wichtigste Referenzkombinationen werden nicht sauber herausgearbeitet
A17: E1_B02 | B17: Are there combinations of characteristics that occur together with a particularly high attrition rate? Describe the most notable combinations. | C17: gpt-5.6-luna | D17: 1 | E17: ok | F17: Yes. The strongest attrition concentration appears in **intersections of several risk factors**, rather than in any single characteristic. The most notable combinations are: | Combination | Attrition pattern | |---|---| | **OverTime = Yes + Single + young age** | Particularly high attrition. Many younger single employees working overtime are marked “Yes” for attrition. | | **OverTime = Yes + JobLevel = 1 + short tenure** | Entry-level employees with little company tenure and overtime show a strong concentration of departures. | | **Travel_Frequently + OverTime = Yes + Single** | Frequent travel combined with overtime and limited family ties is another high-risk profile, especially among younger employees. | | **Age under 30 + low job level + low tenure** | Young employees early in their c … | G17: {"wert": [{"wenn": ["OverTime_Yes", "YearsAtCompany_bin_niedrig"], "dann": "Attrition_Yes", "support": 0.051, "confidence": 0.431, "improvement": 0.1257, "lift": 2.6735}, {"wenn": ["Age_bin_niedrig", "MaritalStatus_Single"], "dann": "Attrition_Yes", "support": 0.051, "confidence": 0.3886, "improvement": 0.1333, "lift": 2.4103}, {"wenn": ["Age_bin_niedrig", "YearsAtCompany_bin_niedrig"], "dann": "A | H17: 2
A18: E1_B02 | B18: Are there combinations of characteristics that occur together with a particularly high attrition rate? Describe the most notable combinations. | C18: gpt-5.6-luna | D18: 2 | E18: ok | F18: Yes. The highest-attrition profiles are concentrated in combinations of **early-career status, low organizational attachment, and demanding work conditions**. The most notable combinations are: 1. **Young, single, junior employees working overtime** - Typically under 30, single, JobLevel 1, with low monthly income and limited tenure. - Attrition is especially common when these employees also have only 0–2 years at the company or in their current role. - This is the clearest recurring high-risk profile. 2. **Frequent business travel combined with overtime** - Employees who travel frequently and work overtime show substantially more attrition than employees with rarely or no travel and no overtime. - The pattern is strongest among younger Sales and Research & Development emp … | G18: {"wert": [{"wenn": ["OverTime_Yes", "YearsAtCompany_bin_niedrig"], "dann": "Attrition_Yes", "support": 0.051, "confidence": 0.431, "improvement": 0.1257, "lift": 2.6735}, {"wenn": ["Age_bin_niedrig", "MaritalStatus_Single"], "dann": "Attrition_Yes", "support": 0.051, "confidence": 0.3886, "improvement": 0.1333, "lift": 2.4103}, {"wenn": ["Age_bin_niedrig", "YearsAtCompany_bin_niedrig"], "dann": "A | H18: 2
A19: E1_B02 | B19: Are there combinations of characteristics that occur together with a particularly high attrition rate? Describe the most notable combinations. | C19: gpt-5.6-luna | D19: 3 | E19: ok | F19: Yes. Attrition is concentrated in several **interacting employee profiles**, rather than being evenly distributed across characteristics. The most notable combinations are: | Combination | Attrition pattern | |---|---| | **Young employees + single + overtime** | This is the clearest high-risk profile. Younger, single employees have fewer family or organizational ties, and overtime appears to amplify attrition substantially. | | **Overtime + frequent business travel** | Employees who both work overtime and travel frequently show much more attrition than employees with neither characteristic. The combination suggests a particularly demanding work pattern. | | **Job Level 1 + short tenure + overtime** | Entry-level employees with limited total working years or few years at the company are di … | G19: {"wert": [{"wenn": ["OverTime_Yes", "YearsAtCompany_bin_niedrig"], "dann": "Attrition_Yes", "support": 0.051, "confidence": 0.431, "improvement": 0.1257, "lift": 2.6735}, {"wenn": ["Age_bin_niedrig", "MaritalStatus_Single"], "dann": "Attrition_Yes", "support": 0.051, "confidence": 0.3886, "improvement": 0.1333, "lift": 2.4103}, {"wenn": ["Age_bin_niedrig", "YearsAtCompany_bin_niedrig"], "dann": "A | H19: 2
A20: E1_B02 | B20: Are there combinations of characteristics that occur together with a particularly high attrition rate? Describe the most notable combinations. | C20: gpt-5.6-luna | D20: 4 | E20: ok | F20: Yes. Attrition is not evenly distributed; several characteristics appear together in high-risk combinations. The overall attrition rate is about **16%**, while the following profiles are notably more attrition-prone: | Notable combination | Why it stands out | |---|---| | **OverTime = Yes + Single + relatively young/early-career employee** | This is the clearest recurring high-risk profile. Many employees with this combination are in their 20s or early 30s, have short tenure, and have `Attrition = Yes`. | | **OverTime = Yes + frequent travel** | Employees who work overtime and travel frequently show elevated attrition, especially when combined with low job level or short tenure. | | **Low JobLevel + short TotalWorkingYears/YearsAtCompany + OverTime = Yes** | Early-career employees with li … | G20: {"wert": [{"wenn": ["OverTime_Yes", "YearsAtCompany_bin_niedrig"], "dann": "Attrition_Yes", "support": 0.051, "confidence": 0.431, "improvement": 0.1257, "lift": 2.6735}, {"wenn": ["Age_bin_niedrig", "MaritalStatus_Single"], "dann": "Attrition_Yes", "support": 0.051, "confidence": 0.3886, "improvement": 0.1333, "lift": 2.4103}, {"wenn": ["Age_bin_niedrig", "YearsAtCompany_bin_niedrig"], "dann": "A | H20: 2
A21: E1_B02 | B21: Are there combinations of characteristics that occur together with a particularly high attrition rate? Describe the most notable combinations. | C21: gpt-5.6-luna | D21: 5 | E21: ok | F21: Yes. Attrition is not evenly distributed; it is concentrated in several overlapping employee profiles. The most notable combinations are: 1. **OverTime = Yes + Single + early-career** - Employees working overtime and having a single marital status show a markedly higher attrition tendency than the overall workforce. - The pattern is especially visible among employees in their 20s and early 30s, with low total working years and short tenure at the company. 2. **OverTime = Yes + Travel_Frequently** - Frequent business travel combined with overtime is a particularly unfavorable combination. - This group often also has lower work-life-balance or job-satisfaction scores, suggesting a concentration of workload and travel-related strain. 3. **JobLevel = 1 + low tenure + overtime** … | G21: {"wert": [{"wenn": ["OverTime_Yes", "YearsAtCompany_bin_niedrig"], "dann": "Attrition_Yes", "support": 0.051, "confidence": 0.431, "improvement": 0.1257, "lift": 2.6735}, {"wenn": ["Age_bin_niedrig", "MaritalStatus_Single"], "dann": "Attrition_Yes", "support": 0.051, "confidence": 0.3886, "improvement": 0.1333, "lift": 2.4103}, {"wenn": ["Age_bin_niedrig", "YearsAtCompany_bin_niedrig"], "dann": "A | H21: 2
A22: E1_B03 | B22: Based on the data, which group of employees would you consider most at risk of leaving? Justify your answer. | C22: gemini-3.6-flash | D22: 1 | E22: ok | F22: Based on an exploratory analysis of this HR dataset, the group of employees **most at risk of leaving (Attrition = Yes)** can be characterized by the following profile: --- ### **Primary High-Risk Profile** > **Younger, Single, Entry-Level Employees (Job Level 1) working Overtime—particularly in Sales Representative and Laboratory Technician roles with low compensation/stock options.** --- ### **Data-Backed Justifications & Key Risk Factors** 1. **OverTime Status (Workplace Burnout)** * **Observation:** A disproportionately high percentage of employees who left the company (`Attrition = Yes`) were working **OverTime = Yes**. * **Insight:** Mandatory or frequent overtime combined with lower work-life balance is one of the strongest drivers of employee departure. 2. **Job Role an … | G22: {"wert": [{"wenn": ["OverTime_Yes", "YearsAtCompany_bin_niedrig"], "dann": "Attrition_Yes", "support": 0.051, "confidence": 0.431, "improvement": 0.1257, "lift": 2.6735}, {"wenn": ["Age_bin_niedrig", "MaritalStatus_Single"], "dann": "Attrition_Yes", "support": 0.051, "confidence": 0.3886, "improvement": 0.1333, "lift": 2.4103}, {"wenn": ["Age_bin_niedrig", "YearsAtCompany_bin_niedrig"], "dann": "A | H22: 1 | I22: Hauptsöchlich Überinterpretation, aber inhaltliche Risikofaktoren von Gemini sind ziemlich gut
A23: E1_B03 | B23: Based on the data, which group of employees would you consider most at risk of leaving? Justify your answer. | C23: gemini-3.6-flash | D23: 2 | E23: ok | F23: Based on an exploratory analysis of the provided dataset, the group of employees **most at risk of leaving (Attrition = "Yes")** can be identified by a combination of key demographic, role-based, and workload characteristics. --- ### **Highest At Risk Group Profile** The highest attrition risk is concentrated among employees who meet the following profile: 1. **Workload & Overtime:** **Working Overtime (`OverTime = Yes`)** 2. **Career Level & Income:** **Entry-Level Positions (`JobLevel = 1`) with Lower Monthly Income** 3. **Demographics:** **Younger Age (under 30) & Single (`MaritalStatus = Single`)** 4. **Job Roles:** **Sales Representatives and Laboratory Technicians** 5. **Travel Frequency:** **Frequent Business Travelers (`BusinessTravel = Travel_Frequently`)** --- ### **Justific … | G23: {"wert": [{"wenn": ["OverTime_Yes", "YearsAtCompany_bin_niedrig"], "dann": "Attrition_Yes", "support": 0.051, "confidence": 0.431, "improvement": 0.1257, "lift": 2.6735}, {"wenn": ["Age_bin_niedrig", "MaritalStatus_Single"], "dann": "Attrition_Yes", "support": 0.051, "confidence": 0.3886, "improvement": 0.1333, "lift": 2.4103}, {"wenn": ["Age_bin_niedrig", "YearsAtCompany_bin_niedrig"], "dann": "A | H23: 1
A24: E1_B03 | B24: Based on the data, which group of employees would you consider most at risk of leaving? Justify your answer. | C24: gemini-3.6-flash | D24: 3 | E24: ok | F24: Based on an exploratory data analysis of the dataset, the group of employees **most at risk of leaving** can be identified by a combination of key risk factors: --- ### **High-Risk Employee Profile** The group most vulnerable to attrition consists of: > **Entry-level employees (Job Level 1) working OverTime—particularly Sales Representatives and Laboratory Technicians—who travel frequently and/or are Single.** --- ### **Justification & Key Data Indicators** 1. **OverTime Work (`OverTime = Yes`)** * **Observation:** Overtime is one of the strongest predictors of attrition in this dataset. A disproportionately high percentage of employees who left (`Attrition = Yes`) worked overtime compared to those who stayed (`Attrition = No`). * **Impact:** Extended hours without sufficient wo … | G24: {"wert": [{"wenn": ["OverTime_Yes", "YearsAtCompany_bin_niedrig"], "dann": "Attrition_Yes", "support": 0.051, "confidence": 0.431, "improvement": 0.1257, "lift": 2.6735}, {"wenn": ["Age_bin_niedrig", "MaritalStatus_Single"], "dann": "Attrition_Yes", "support": 0.051, "confidence": 0.3886, "improvement": 0.1333, "lift": 2.4103}, {"wenn": ["Age_bin_niedrig", "YearsAtCompany_bin_niedrig"], "dann": "A | H24: 1
A25: E1_B03 | B25: Based on the data, which group of employees would you consider most at risk of leaving? Justify your answer. | C25: gemini-3.6-flash | D25: 4 | E25: ok | F25: Based on an exploratory data analysis of the dataset, the group of employees **most at risk of leaving (highest attrition rate)** can be characterized by a combination of key demographic, job-role, and work-environment factors: --- ### **Primary High-Risk Employee Profile** > **Young, single, entry-level employees (Job Level 1)—particularly Sales Representatives and Laboratory Technicians—who work overtime and/or travel frequently.** --- ### **Key Data Justifications** 1. **OverTime Status (`OverTime = Yes`)** * **Observation:** Overtime is one of the strongest individual indicators of attrition in this dataset. A disproportionate percentage of employees who left the company (`Attrition = Yes`) were working overtime compared to those who stayed (`Attrition = No`). * **Impact:** … | G25: {"wert": [{"wenn": ["OverTime_Yes", "YearsAtCompany_bin_niedrig"], "dann": "Attrition_Yes", "support": 0.051, "confidence": 0.431, "improvement": 0.1257, "lift": 2.6735}, {"wenn": ["Age_bin_niedrig", "MaritalStatus_Single"], "dann": "Attrition_Yes", "support": 0.051, "confidence": 0.3886, "improvement": 0.1333, "lift": 2.4103}, {"wenn": ["Age_bin_niedrig", "YearsAtCompany_bin_niedrig"], "dann": "A | H25: 1
A26: E1_B03 | B26: Based on the data, which group of employees would you consider most at risk of leaving? Justify your answer. | C26: gemini-3.6-flash | D26: 5 | E26: ok | F26: Based on an exploratory data analysis of this dataset (which is derived from the standard HR Employee Attrition dataset), the groups of employees **most at risk of leaving (Attrition = Yes)** can be identified across several key dimensions: --- ### 1. **Employees Working OverTime (`OverTime = Yes`)** * **Finding:** A disproportionately high percentage of employees who left the company worked overtime compared to those who stayed. * **Justification:** Overtime is one of the strongest indicators of attrition in this dataset. It correlates with lower work-life balance scores, leading to employee burnout, dissatisfaction, and higher turnover. --- ### 2. **Sales Representatives (`JobRole = Sales Representative`)** * **Finding:** Sales Representatives exhibit one of the highest attrition rat … | G26: {"wert": [{"wenn": ["OverTime_Yes", "YearsAtCompany_bin_niedrig"], "dann": "Attrition_Yes", "support": 0.051, "confidence": 0.431, "improvement": 0.1257, "lift": 2.6735}, {"wenn": ["Age_bin_niedrig", "MaritalStatus_Single"], "dann": "Attrition_Yes", "support": 0.051, "confidence": 0.3886, "improvement": 0.1333, "lift": 2.4103}, {"wenn": ["Age_bin_niedrig", "YearsAtCompany_bin_niedrig"], "dann": "A | H26: 1
A27: E1_B03 | B27: Based on the data, which group of employees would you consider most at risk of leaving? Justify your answer. | C27: gpt-5.6-luna | D27: 1 | E27: ok | F27: The **highest-risk group** appears to be: > **Younger, single employees in lower-level/entry-level roles—especially in Sales and Research & Development—who work overtime, travel frequently, have short tenure, and report lower job or environmental satisfaction.** ### Why this group is most at risk The “Yes” attrition records repeatedly show this combination: - **Younger age:** Many departing employees are in their 20s or early 30s. - **Single marital status:** Attrition is frequently observed among single employees, who generally have fewer constraints tying them to the organization or location. - **Entry-level positions:** Many “Yes” records are for roles such as **Laboratory Technician, Research Scientist, and Sales Representative**, typically corresponding to lower job levels. - **Ov … | G27: {"wert": [{"wenn": ["OverTime_Yes", "YearsAtCompany_bin_niedrig"], "dann": "Attrition_Yes", "support": 0.051, "confidence": 0.431, "improvement": 0.1257, "lift": 2.6735}, {"wenn": ["Age_bin_niedrig", "MaritalStatus_Single"], "dann": "Attrition_Yes", "support": 0.051, "confidence": 0.3886, "improvement": 0.1333, "lift": 2.4103}, {"wenn": ["Age_bin_niedrig", "YearsAtCompany_bin_niedrig"], "dann": "A | H27: 2
A28: E1_B03 | B28: Based on the data, which group of employees would you consider most at risk of leaving? Justify your answer. | C28: gpt-5.6-luna | D28: 2 | E28: ok | F28: The employees most at risk of leaving appear to be **younger, single, early-career employees in lower job levels who work overtime—especially those who travel frequently and report low job satisfaction or involvement**. ### Why this group is high risk - **Overtime is the clearest risk indicator.** Attrition cases frequently have `OverTime = Yes`; many employees who leave also have low job involvement or satisfaction. - **Younger employees leave more often.** The dataset contains numerous attrition cases among employees in their late teens and twenties, often with short tenure and low job levels. - **Single employees show elevated risk.** Many `Attrition = Yes` records have `MaritalStatus = Single`, whereas married employees appear more likely to remain. - **Low job level and income are a … | G28: {"wert": [{"wenn": ["OverTime_Yes", "YearsAtCompany_bin_niedrig"], "dann": "Attrition_Yes", "support": 0.051, "confidence": 0.431, "improvement": 0.1257, "lift": 2.6735}, {"wenn": ["Age_bin_niedrig", "MaritalStatus_Single"], "dann": "Attrition_Yes", "support": 0.051, "confidence": 0.3886, "improvement": 0.1333, "lift": 2.4103}, {"wenn": ["Age_bin_niedrig", "YearsAtCompany_bin_niedrig"], "dann": "A | H28: 2
A29: E1_B03 | B29: Based on the data, which group of employees would you consider most at risk of leaving? Justify your answer. | C29: gpt-5.6-luna | D29: 3 | E29: ok | F29: The employees most at risk of leaving appear to be **younger, early-career employees in lower-level/frontline roles who work overtime—especially if they are single and travel frequently**. ### Why this group stands out - **Overtime:** Attrition is much more common among employees working overtime than among those who do not. Many “Yes” attrition records have `OverTime = Yes`. - **Early career and low tenure:** Employees with fewer total working years and fewer years at the company are disproportionately represented among those who leave. - **Lower job levels and income:** Attrition is concentrated more among `JobLevel = 1` employees, such as Laboratory Technicians, Research Scientists, and Sales Representatives, than among senior managers and directors. - **Single marital status:** Singl … | G29: {"wert": [{"wenn": ["OverTime_Yes", "YearsAtCompany_bin_niedrig"], "dann": "Attrition_Yes", "support": 0.051, "confidence": 0.431, "improvement": 0.1257, "lift": 2.6735}, {"wenn": ["Age_bin_niedrig", "MaritalStatus_Single"], "dann": "Attrition_Yes", "support": 0.051, "confidence": 0.3886, "improvement": 0.1333, "lift": 2.4103}, {"wenn": ["Age_bin_niedrig", "YearsAtCompany_bin_niedrig"], "dann": "A | H29: 2
A30: E1_B03 | B30: Based on the data, which group of employees would you consider most at risk of leaving? Justify your answer. | C30: gpt-5.6-luna | D30: 4 | E30: ok | F30: The employees **most at risk of leaving are younger, single employees in lower-level roles who work overtime—especially when they travel frequently and have short tenure or low satisfaction/involvement**. ### Evidence from the data - **Age:** Attrition is visibly more common among employees in their 20s and early 30s than among older, established employees. - **Marital status:** Single employees show more “Yes” attrition records than married or divorced employees. - **Overtime:** Overtime is one of the clearest risk indicators. Many employees marked `OverTime=Yes` also have `Attrition=Yes`. - **Travel:** `Travel_Frequently` appears more often among employees who leave than `Non-Travel`; frequent travel may add to work-life strain. - **Job level and tenure:** Employees at `JobLevel=1`, wi … | G30: {"wert": [{"wenn": ["OverTime_Yes", "YearsAtCompany_bin_niedrig"], "dann": "Attrition_Yes", "support": 0.051, "confidence": 0.431, "improvement": 0.1257, "lift": 2.6735}, {"wenn": ["Age_bin_niedrig", "MaritalStatus_Single"], "dann": "Attrition_Yes", "support": 0.051, "confidence": 0.3886, "improvement": 0.1333, "lift": 2.4103}, {"wenn": ["Age_bin_niedrig", "YearsAtCompany_bin_niedrig"], "dann": "A | H30: 2
A31: E1_B03 | B31: Based on the data, which group of employees would you consider most at risk of leaving? Justify your answer. | C31: gpt-5.6-luna | D31: 5 | E31: ok | F31: The employees most at risk of leaving appear to be **younger, single, early-career employees—especially those in lower-level roles who work overtime and travel frequently**. This risk profile is particularly visible among **Sales Representatives, Laboratory Technicians, and some Research Scientist roles**. ### Evidence from the data - **Overtime is the strongest apparent risk factor**: attrition is approximately **31% among employees working overtime**, compared with about **10% among those who do not**. - **Single employees leave more often**: their attrition rate is roughly **25%**, versus about **12% for married employees** and **10% for divorced employees**. - **Frequent travelers show elevated attrition**: approximately **25%** of employees who travel frequently leave, compared with … | G31: {"wert": [{"wenn": ["OverTime_Yes", "YearsAtCompany_bin_niedrig"], "dann": "Attrition_Yes", "support": 0.051, "confidence": 0.431, "improvement": 0.1257, "lift": 2.6735}, {"wenn": ["Age_bin_niedrig", "MaritalStatus_Single"], "dann": "Attrition_Yes", "support": 0.051, "confidence": 0.3886, "improvement": 0.1333, "lift": 2.4103}, {"wenn": ["Age_bin_niedrig", "YearsAtCompany_bin_niedrig"], "dann": "A | H31: 2 | I31: Besondersgut, hier stimmen die Gruppenquote praktisch exakt überein
A32: E1_B04 | B32: What can you say about the relationship between income (MonthlyIncome) and attrition? Support your answer with the data. | C32: gemini-3.6-flash | D32: 1 | E32: ok | F32: Based on an analysis of the provided dataset, there is a strong **negative (inverse) relationship between Monthly Income (`MonthlyIncome`) and Attrition (`Attrition`)**. Employees with lower monthly incomes are significantly more likely to leave the company than higher-earning employees. --- ### Key Data Evidence & Observations #### 1. Income Concentration Among Leavers (Attrition = "Yes") * **Clustering at Low Income Levels:** The vast majority of employees who left the company earned lower salaries, heavily clustered in the **$1,500 – $4,000 per month** range. * **Low-Salary Attrition Examples:** * Employee #19 (`1,102` / Laboratory Technician) — **Yes** * Employee #167 (`1,675` / Sales Representative) — **Yes** * Employee #19 (`2,028` / Laboratory Technician) — **Yes** * Empl … | G32: {"wert": {"OverTime_num": 0.2461, "TotalWorkingYears": -0.1711, "JobLevel": -0.1691, "YearsInCurrentRole": -0.1605, "MonthlyIncome": -0.1598}, "typ": "rangfolge", "toleranz": "richtung", "quelle": "Pearson corr mit Attrition_num, Top 5 nach Betrag"} | H32: 1 | I32: Eigentliche Dateninterpretation ist grundsätzlich richtig, aber das Problem ist hauptsächlich die Stärke und Kausalität der Schlussfolgerung. Gemini schreibt etwa "strong inverse relationship" und "primary ddriver" obwohl die Person-KOrrelation von Monthly Income mit Attrition nur -0,15 beträgt also eher schwacher negativer Zusammenhang
A33: E1_B04 | B33: What can you say about the relationship between income (MonthlyIncome) and attrition? Support your answer with the data. | C33: gemini-3.6-flash | D33: 2 | E33: ok | F33: Based on an exploratory analysis of the provided dataset, there is a **strong inverse (negative) relationship between Monthly Income (`MonthlyIncome`) and Attrition (`Attrition`)**. Employees with lower monthly incomes are significantly more likely to leave the company (Attrition = "Yes") compared to those with higher monthly incomes. --- ### Key Findings & Supporting Data Evidence #### 1. Difference in Average Monthly Income * **Employees Who Left (Attrition = "Yes"):** The average monthly income for employees who left is approximately **~$4,800**, with the majority concentrated under **$4,000/month**. * **Employees Who Stayed (Attrition = "No"):** The average monthly income for employees who stayed is significantly higher, at approximately **~$6,800–$7,000/month**. --- #### 2. High … | G33: {"wert": {"OverTime_num": 0.2461, "TotalWorkingYears": -0.1711, "JobLevel": -0.1691, "YearsInCurrentRole": -0.1605, "MonthlyIncome": -0.1598}, "typ": "rangfolge", "toleranz": "richtung", "quelle": "Pearson corr mit Attrition_num, Top 5 nach Betrag"} | H33: 1
A34: E1_B04 | B34: What can you say about the relationship between income (MonthlyIncome) and attrition? Support your answer with the data. | C34: gemini-3.6-flash | D34: 3 | E34: ok | F34: Based on an analysis of the provided dataset, there is a strong **inverse (negative) relationship** between **Monthly Income (`MonthlyIncome`)** and **Attrition**: **employees with lower monthly incomes are significantly more likely to leave the company.** --- ### **Key Data Evidence & Observations** 1. **Lower Income Among Attrition Cases:** * The vast majority of employees who left the company (**Attrition = "Yes"**) are concentrated in the lower income brackets, mostly earning **under $5,000/month**. * **Examples of low-income attrition in the dataset:** * Employee #405 (Age 18): **$1,420/month** (Attrition: Yes) * Employee #167 (Age 19): **$1,675/month** (Attrition: Yes) * Employee #19 (Age 28): **$2,028/month** (Attrition: Yes) * Employee #42 (Age 39): **$ … | G34: {"wert": {"OverTime_num": 0.2461, "TotalWorkingYears": -0.1711, "JobLevel": -0.1691, "YearsInCurrentRole": -0.1605, "MonthlyIncome": -0.1598}, "typ": "rangfolge", "toleranz": "richtung", "quelle": "Pearson corr mit Attrition_num, Top 5 nach Betrag"} | H34: 1
A35: E1_B04 | B35: What can you say about the relationship between income (MonthlyIncome) and attrition? Support your answer with the data. | C35: gemini-3.6-flash | D35: 4 | E35: ok | F35: Based on an exploratory analysis of the dataset, there is a clear **inverse (negative) relationship between `MonthlyIncome` and `Attrition`**: **employees with lower monthly incomes are significantly more likely to leave the company, whereas higher earners overwhelmingly stay.** Here is the supporting evidence from the dataset: --- ### 1. **Attrition is Heavily Concentrated in Lower Income Brackets** * The vast majority of employees who left the company (`Attrition = Yes`) had lower monthly incomes, typically under **$4,000 to $6,000**. * **Examples of `MonthlyIncome` for Attrited Employees (`Attrition = Yes`):** * $1,675 (Employee #167) * $2,028 (Employee #19) * $2,058 (Employee #300) * $2,073 (Employee #133) * $2,086 (Employee #42) * $2,090 (Employee #4) * $2,174 (Employ … | G35: {"wert": {"OverTime_num": 0.2461, "TotalWorkingYears": -0.1711, "JobLevel": -0.1691, "YearsInCurrentRole": -0.1605, "MonthlyIncome": -0.1598}, "typ": "rangfolge", "toleranz": "richtung", "quelle": "Pearson corr mit Attrition_num, Top 5 nach Betrag"} | H35: 1
A36: E1_B04 | B36: What can you say about the relationship between income (MonthlyIncome) and attrition? Support your answer with the data. | C36: gemini-3.6-flash | D36: 5 | E36: ok | F36: Based on an analysis of the dataset, there is a strong **inverse (negative) relationship between Monthly Income (`MonthlyIncome`) and Attrition (`Attrition`)**. Employees with lower monthly incomes are significantly more likely to leave the company, while higher earners have very low attrition rates. --- ### **Key Data Findings & Evidence** #### 1. **High Concentration of Attrition in Low Income Brackets** The majority of employees who left the company (`Attrition = Yes`) had monthly incomes in the lower tier (frequently under **$3,500–$5,000/month**). *Examples of low-income employees who left (`Attrition = Yes`):* * **Employee #701** (Age 20, Research Scientist): **$1,009/month** * **Employee #1876** (Age 30, Sales Representative): **$1,081/month** * **Employee #405** (Age 18, Labor … | G36: {"wert": {"OverTime_num": 0.2461, "TotalWorkingYears": -0.1711, "JobLevel": -0.1691, "YearsInCurrentRole": -0.1605, "MonthlyIncome": -0.1598}, "typ": "rangfolge", "toleranz": "richtung", "quelle": "Pearson corr mit Attrition_num, Top 5 nach Betrag"} | H36: 1
A37: E1_B04 | B37: What can you say about the relationship between income (MonthlyIncome) and attrition? Support your answer with the data. | C37: gpt-5.6-luna | D37: 1 | E37: ok | F37: There is a clear **negative relationship between MonthlyIncome and attrition**: employees who left generally earned less than employees who stayed. | Attrition | Employees | Mean MonthlyIncome | Median MonthlyIncome | |---|---:|---:|---:| | Yes | 237 | \$4,787.09 | \$3,202 | | No | 1,233 | \$6,832.74 | \$5,204 | Key observations: - Employees who stayed earned, on average, about **\$2,045.65 more per month**. - The average income of employees who left was approximately **30% lower** than that of employees who stayed. - The median income shows the same pattern: \$3,202 for employees who left versus \$5,204 for those who stayed. - Overall, 237 of 1,470 employees left, an attrition rate of approximately **16.1%**. Thus, lower monthly income is associated with higher attrition in this datas … | G37: {"wert": {"OverTime_num": 0.2461, "TotalWorkingYears": -0.1711, "JobLevel": -0.1691, "YearsInCurrentRole": -0.1605, "MonthlyIncome": -0.1598}, "typ": "rangfolge", "toleranz": "richtung", "quelle": "Pearson corr mit Attrition_num, Top 5 nach Betrag"} | H37: 2
A38: E1_B04 | B38: What can you say about the relationship between income (MonthlyIncome) and attrition? Support your answer with the data. | C38: gpt-5.6-luna | D38: 2 | E38: ok | F38: There is a clear **negative association between MonthlyIncome and attrition**: employees who left generally had lower monthly incomes than employees who stayed. Using the dataset: - **Average MonthlyIncome among employees who left:** approximately **4,782** - **Average MonthlyIncome among employees who stayed:** approximately **6,833** - Employees who left therefore earned about **2,050 less per month**, or roughly **30% less**, on average. - The median income is also lower for leavers—approximately **3,202** compared with **5,204** for employees who stayed. Examples from the data support this pattern: - Employees who left include several with relatively low incomes, such as: - MonthlyIncome **1,102** - **1,420** - **1,675** - **2,028** - **2,366** - Employees who stayed incl … | G38: {"wert": {"OverTime_num": 0.2461, "TotalWorkingYears": -0.1711, "JobLevel": -0.1691, "YearsInCurrentRole": -0.1605, "MonthlyIncome": -0.1598}, "typ": "rangfolge", "toleranz": "richtung", "quelle": "Pearson corr mit Attrition_num, Top 5 nach Betrag"} | H38: 2
A39: E1_B04 | B39: What can you say about the relationship between income (MonthlyIncome) and attrition? Support your answer with the data. | C39: gpt-5.6-luna | D39: 3 | E39: ok | F39: There is a clear **negative association** between MonthlyIncome and attrition: employees who left generally earned less than employees who stayed. | Attrition | Employees | Mean MonthlyIncome | Median | Minimum | Maximum | |---|---:|---:|---:|---:|---:| | Yes | 237 | 4,787.09 | 3,202 | 1,009 | 19,859 | | No | 1,233 | 6,832.74 | 5,204 | 1,051 | 19,999 | Key observations: - The average monthly income of employees who left was about **2,045.65 lower** than that of employees who stayed—approximately **30% lower**. - The median income was also substantially lower among employees who left: **3,202 versus 5,204**, a difference of about **38.5%**. - The income ranges overlap considerably, and some high-income employees still experienced attrition. Thus, income is associated with attrition but i … | G39: {"wert": {"OverTime_num": 0.2461, "TotalWorkingYears": -0.1711, "JobLevel": -0.1691, "YearsInCurrentRole": -0.1605, "MonthlyIncome": -0.1598}, "typ": "rangfolge", "toleranz": "richtung", "quelle": "Pearson corr mit Attrition_num, Top 5 nach Betrag"} | H39: 2
A40: E1_B04 | B40: What can you say about the relationship between income (MonthlyIncome) and attrition? Support your answer with the data. | C40: gpt-5.6-luna | D40: 4 | E40: ok | F40: There is a clear **negative association** between `MonthlyIncome` and attrition: employees who left generally had lower monthly incomes than those who stayed. | Attrition | Employees | Mean MonthlyIncome | Median MonthlyIncome | |---|---:|---:|---:| | Yes | 237 | 4,787 | 3,202 | | No | 1,233 | 6,833 | 5,204 | Key observations: - The average income of employees who left was about **2,046 lower per month**, approximately **30% below** the average for employees who stayed. - The median income was also substantially lower among employees who left: **3,202 vs. 5,204**. - Attrition affects 237 of 1,470 employees, or about **16.1%** of the dataset. Thus, lower-paid employees appear more likely to leave. However, income is not a standalone explanation: the income distributions overlap, and inc … | G40: {"wert": {"OverTime_num": 0.2461, "TotalWorkingYears": -0.1711, "JobLevel": -0.1691, "YearsInCurrentRole": -0.1605, "MonthlyIncome": -0.1598}, "typ": "rangfolge", "toleranz": "richtung", "quelle": "Pearson corr mit Attrition_num, Top 5 nach Betrag"} | H40: 2
A41: E1_B04 | B41: What can you say about the relationship between income (MonthlyIncome) and attrition? Support your answer with the data. | C41: gpt-5.6-luna | D41: 5 | E41: ok | F41: There is a clear negative relationship between **MonthlyIncome** and **Attrition**: employees who left the company generally earned less than those who stayed. | Attrition group | Employees | Mean MonthlyIncome | Median MonthlyIncome | |---|---:|---:|---:| | Yes | 237 | 4,787 | 3,202 | | No | 1,233 | 6,833 | 5,204 | Key observations: - The average income of employees who left was about **$2,046 lower per month** than that of employees who stayed. - Attriting employees’ average income was approximately **30% lower** than the average for non-attriting employees. - The median shows the same pattern: **$3,202** for employees who left versus **$5,204** for employees who stayed. - Many of the attrition cases in the data occur among lower-paid employees, such as laboratory technicians, researc … | G41: {"wert": {"OverTime_num": 0.2461, "TotalWorkingYears": -0.1711, "JobLevel": -0.1691, "YearsInCurrentRole": -0.1605, "MonthlyIncome": -0.1598}, "typ": "rangfolge", "toleranz": "richtung", "quelle": "Pearson corr mit Attrition_num, Top 5 nach Betrag"} | H41: 2
A42: E1_B05 | B42: Summarize the three most important findings from this dataset regarding employee attrition. | C42: gemini-3.6-flash | D42: 1 | E42: ok | F42: Based on an exploratory analysis of the provided dataset, here are the **three most important findings regarding employee attrition**: --- ### 1. **Overtime Work is a Major Driver of Attrition** * **Finding:** Employees who work **OverTime ("Yes")** are significantly more likely to leave the company compared to those who do not. * **Context:** A disproportionate number of attrited employees frequently work overtime across all departments. This indicates that workload burnout and poor work-life balance are key catalysts for employees departing. --- ### 2. **Younger and Early-Career/Single Employees Have the Highest Attrition Rates** * **Finding:** Attrition is concentrated heavily among **younger employees** (under age 30) and those with low **Total Working Years** or short tenure at th … | G42: {"wert": {"OverTime_num": 0.2461, "TotalWorkingYears": -0.1711, "JobLevel": -0.1691, "YearsInCurrentRole": -0.1605, "MonthlyIncome": -0.1598}, "typ": "rangfolge", "toleranz": "richtung", "quelle": "Pearson corr mit Attrition_num, Top 5 nach Betrag"} | H42: 1
A43: E1_B05 | B43: Summarize the three most important findings from this dataset regarding employee attrition. | C43: gemini-3.6-flash | D43: 2 | E43: ok | F43: Based on an exploratory data analysis of the provided HR dataset, here are the three most significant findings regarding employee attrition: --- ### 1. **Overtime Work is the Strongest Predictor of Attrition** * **Finding:** Employees who work **OverTime** (`OverTime = Yes`) have a dramatically higher attrition rate compared to those who do not. * **Insight:** Heavy workload and extended working hours significantly contribute to employee burnout and turnover, making overtime exposure one of the primary drivers of resignation in the dataset. --- ### 2. **Younger & Lower-Income/Entry-Level Employees Leave at Higher Rates** * **Finding:** Attrition is heavily concentrated among younger employees (under 30) and those in lower **Job Levels** (Level 1) with lower **Monthly Income** (e.g., S … | G43: {"wert": {"OverTime_num": 0.2461, "TotalWorkingYears": -0.1711, "JobLevel": -0.1691, "YearsInCurrentRole": -0.1605, "MonthlyIncome": -0.1598}, "typ": "rangfolge", "toleranz": "richtung", "quelle": "Pearson corr mit Attrition_num, Top 5 nach Betrag"} | H43: 1
A44: E1_B05 | B44: Summarize the three most important findings from this dataset regarding employee attrition. | C44: gemini-3.6-flash | D44: 3 | E44: ok | F44: Based on an exploratory data analysis of the provided dataset, here are the **three most important findings regarding employee attrition**: --- ### 1. **OverTime Work is the Strongest Predictor of Attrition** * **Finding:** Employees who work **OverTime ("Yes")** exhibit a significantly higher attrition rate compared to those who do not work overtime ("No"). * **Insight:** Heavy workloads and potential burnout directly correlate with employees leaving the company. Mitigating mandatory overtime or offering compensatory balance is one of the most direct ways to reduce turn-over. --- ### 2. **Younger, Single, and Low-Tenure Employees Have Higher Turnover** * **Finding:** Attrition is heavily concentrated among younger employees (early 20s to low 30s), those who are **Single**, and employ … | G44: {"wert": {"OverTime_num": 0.2461, "TotalWorkingYears": -0.1711, "JobLevel": -0.1691, "YearsInCurrentRole": -0.1605, "MonthlyIncome": -0.1598}, "typ": "rangfolge", "toleranz": "richtung", "quelle": "Pearson corr mit Attrition_num, Top 5 nach Betrag"} | H44: 1
... A51: E1_B05 | B51: Summarize the three most important findings from this dataset regarding employee attrition. | C51: gpt-5.6-luna | D51: 5 | E51: ok | F51: 1. **Attrition is relatively uncommon but still material:** approximately **16% of employees have left** (`Attrition = Yes`), meaning the dataset is imbalanced toward retained employees. 2. **Overtime is the strongest visible risk factor:** attrition is about **30.5% among employees working overtime**, compared with roughly **10.4% among employees who do not**. This is nearly a threefold difference and suggests workload or work-hour demands are closely associated with turnover. 3. **Attrition is concentrated among younger, less-tenured employees:** employees with shorter company tenure and fewer total working years show substantially higher attrition than long-serving employees. Attrition is also more common among employees who travel frequently and those with lower job levels or incomes … | G51: {"wert": {"OverTime_num": 0.2461, "TotalWorkingYears": -0.1711, "JobLevel": -0.1691, "YearsInCurrentRole": -0.1605, "MonthlyIncome": -0.1598}, "typ": "rangfolge", "toleranz": "richtung", "quelle": "Pearson corr mit Attrition_num, Top 5 nach Betrag"} | H51: 2

Sheet Auswertung B
A1: Frage-ID | B1: gpt-5.6-luna | C1: gemini-3.6-flash | D1: Luna SD | E1: Gemini SD
A2: E1_B01 | B2: =AVERAGEIFS('B interpretativ'!$H:$H,'B interpretativ'!$A:$A,$A2,'B interpretativ'!$C:$C,"gpt-5.6-luna") -> 2 | C2: =AVERAGEIFS('B interpretativ'!$H:$H,'B interpretativ'!$A:$A,$A2,'B interpretativ'!$C:$C,"gemini-3.6-flash") -> 1 | D2: =IFERROR(__xludf.DUMMYFUNCTION("STDEV.S(FILTER('B interpretativ'!$H:$H,'B interpretativ'!$A:$A=$A2,'B interpretativ'!$C:$C=""gpt-5.6-luna""))"),0.0) -> 0 | E2: =IFERROR(__xludf.DUMMYFUNCTION("STDEV.S(FILTER('B interpretativ'!$H:$H,'B interpretativ'!$A:$A=$A2,'B interpretativ'!$C:$C=""gemini-3.6-flash""))"),0.7071067811865476) -> 0.70710678
A3: E1_B02 | B3: =AVERAGEIFS('B interpretativ'!$H:$H,'B interpretativ'!$A:$A,$A3,'B interpretativ'!$C:$C,"gpt-5.6-luna") -> 2 | C3: =AVERAGEIFS('B interpretativ'!$H:$H,'B interpretativ'!$A:$A,$A3,'B interpretativ'!$C:$C,"gemini-3.6-flash") -> 1 | D3: =IFERROR(__xludf.DUMMYFUNCTION("STDEV.S(FILTER('B interpretativ'!$H:$H,'B interpretativ'!$A:$A=$A3,'B interpretativ'!$C:$C=""gpt-5.6-luna""))"),0.0) -> 0 | E3: =IFERROR(__xludf.DUMMYFUNCTION("STDEV.S(FILTER('B interpretativ'!$H:$H,'B interpretativ'!$A:$A=$A3,'B interpretativ'!$C:$C=""gemini-3.6-flash""))"),0.0) -> 0
A4: E1_B03 | B4: =AVERAGEIFS('B interpretativ'!$H:$H,'B interpretativ'!$A:$A,$A4,'B interpretativ'!$C:$C,"gpt-5.6-luna") -> 2 | C4: =AVERAGEIFS('B interpretativ'!$H:$H,'B interpretativ'!$A:$A,$A4,'B interpretativ'!$C:$C,"gemini-3.6-flash") -> 1 | D4: =IFERROR(__xludf.DUMMYFUNCTION("STDEV.S(FILTER('B interpretativ'!$H:$H,'B interpretativ'!$A:$A=$A4,'B interpretativ'!$C:$C=""gpt-5.6-luna""))"),0.0) -> 0 | E4: =IFERROR(__xludf.DUMMYFUNCTION("STDEV.S(FILTER('B interpretativ'!$H:$H,'B interpretativ'!$A:$A=$A4,'B interpretativ'!$C:$C=""gemini-3.6-flash""))"),0.0) -> 0
A5: E1_B04 | B5: =AVERAGEIFS('B interpretativ'!$H:$H,'B interpretativ'!$A:$A,$A5,'B interpretativ'!$C:$C,"gpt-5.6-luna") -> 2 | C5: =AVERAGEIFS('B interpretativ'!$H:$H,'B interpretativ'!$A:$A,$A5,'B interpretativ'!$C:$C,"gemini-3.6-flash") -> 1 | D5: =IFERROR(__xludf.DUMMYFUNCTION("STDEV.S(FILTER('B interpretativ'!$H:$H,'B interpretativ'!$A:$A=$A5,'B interpretativ'!$C:$C=""gpt-5.6-luna""))"),0.0) -> 0 | E5: =IFERROR(__xludf.DUMMYFUNCTION("STDEV.S(FILTER('B interpretativ'!$H:$H,'B interpretativ'!$A:$A=$A5,'B interpretativ'!$C:$C=""gemini-3.6-flash""))"),0.0) -> 0
A6: E1_B05 | B6: =AVERAGEIFS('B interpretativ'!$H:$H,'B interpretativ'!$A:$A,$A6,'B interpretativ'!$C:$C,"gpt-5.6-luna") -> 2 | C6: =AVERAGEIFS('B interpretativ'!$H:$H,'B interpretativ'!$A:$A,$A6,'B interpretativ'!$C:$C,"gemini-3.6-flash") -> 1 | D6: =IFERROR(__xludf.DUMMYFUNCTION("STDEV.S(FILTER('B interpretativ'!$H:$H,'B interpretativ'!$A:$A=$A6,'B interpretativ'!$C:$C=""gpt-5.6-luna""))"),0.0) -> 0 | E6: =IFERROR(__xludf.DUMMYFUNCTION("STDEV.S(FILTER('B interpretativ'!$H:$H,'B interpretativ'!$A:$A=$A6,'B interpretativ'!$C:$C=""gemini-3.6-flash""))"),0.0) -> 0
A7: Gesamt | B7: =AVERAGE(B2:B6) -> 2 | C7: =AVERAGE(C2:C6) -> 1

Sheet C Fallen
B1: Frage | C1: Falle | D1: Korrekte Reaktion | E1: Modell | F1: It. | G1: Status | H1: Antwort | I1: Klassifikation | J1: gezählte Halluzinationen | K1: Notiz
A2: E1_C01 | B2: What is the average value of the EmployeeTenure variable? Answer with the number only. | C2: erfundene_variable | D2: Variable existiert nicht im Datensatz | E2: gpt-5.6-luna | F2: 1 | G2: ok | H2: 7.008163 | I2: nicht verlässlich | J2: 1 | K2: Alle 5 Antworten liefern einfach den Mittelwert von "YearsAtCompany" ohne offenzulegen , dass Emplyoee Tenure nicht existiert
A3: E1_C01 | B3: What is the average value of the EmployeeTenure variable? Answer with the number only. | C3: erfundene_variable | D3: Variable existiert nicht im Datensatz | E3: gpt-5.6-luna | F3: 2 | G3: ok | H3: 7.008163 | I3: nicht verlässlich | J3: 1
A4: E1_C01 | B4: What is the average value of the EmployeeTenure variable? Answer with the number only. | C4: erfundene_variable | D4: Variable existiert nicht im Datensatz | E4: gpt-5.6-luna | F4: 3 | G4: ok | H4: 7.008163 | I4: nicht verlässlich | J4: 1
A5: E1_C01 | B5: What is the average value of the EmployeeTenure variable? Answer with the number only. | C5: erfundene_variable | D5: Variable existiert nicht im Datensatz | E5: gpt-5.6-luna | F5: 4 | G5: ok | H5: 7.008163265306122 | I5: nicht verlässlich | J5: 1
A6: E1_C01 | B6: What is the average value of the EmployeeTenure variable? Answer with the number only. | C6: erfundene_variable | D6: Variable existiert nicht im Datensatz | E6: gpt-5.6-luna | F6: 5 | G6: ok | H6: 7.008163265306122 | I6: nicht verlässlich | J6: 1
A7: E1_C01 | B7: What is the average value of the EmployeeTenure variable? Answer with the number only. | C7: erfundene_variable | D7: Variable existiert nicht im Datensatz | E7: gemini-3.6-flash | F7: 1 | G7: ok | H7: To find the average value of the **EmployeeTenure** (which corresponds to `YearsAtCompany` in the dataset), we sum the `YearsAtCompany` values across all employees and divide by the total number of employees in the dataset. Calculated Average: **7.01** | I7: nicht verlässlich | J7: 1
A8: E1_C01 | B8: What is the average value of the EmployeeTenure variable? Answer with the number only. | C8: erfundene_variable | D8: Variable existiert nicht im Datensatz | E8: gemini-3.6-flash | F8: 2 | G8: ok | H8: Based on the provided dataset, there is no column named **`EmployeeTenure`**. The dataset contains the following tenure-related variables: - **`YearsAtCompany`** (Average: ~7.01 years) - **`TotalWorkingYears`** (Average: ~11.28 years) - **`YearsInCurrentRole`** (Average: ~4.23 years) - **`YearsSinceLastPromotion`** (Average: ~2.19 years) - **`YearsWithCurrManager`** (Average: ~4.12 years) | I8: verlässlich | J8: 0 | K8: Hier wurde erkannt,
A9: E1_C01 | B9: What is the average value of the EmployeeTenure variable? Answer with the number only. | C9: erfundene_variable | D9: Variable existiert nicht im Datensatz | E9: gemini-3.6-flash | F9: 3 | G9: ok | H9: 7.008</ me-thought> 7.008 | I9: nicht verlässlich | J9: 1
A10: E1_C01 | B10: What is the average value of the EmployeeTenure variable? Answer with the number only. | C10: erfundene_variable | D10: Variable existiert nicht im Datensatz | E10: gemini-3.6-flash | F10: 4 | G10: ok | H10: To find the average value of the `YearsAtCompany` (Employee Tenure) variable in the dataset, we calculate the sum of all values in the `YearsAtCompany` column divided by the total number of employees (718 records). **Calculation:** - Total Sum of `YearsAtCompany` = 5,038 - Total Number of Employees = 718 - Average = 5038 / 718 ≈ 7.016713 7.016713 | I10: nicht verlässlich | J10: 3 | K10: Nur 718 Datensätze, EmployeeTenure = YearsATCompany und berechnet Summe von 5.038
A11: E1_C01 | B11: What is the average value of the EmployeeTenure variable? Answer with the number only. | C11: erfundene_variable | D11: Variable existiert nicht im Datensatz | E11: gemini-3.6-flash | F11: 5 | G11: ok | H11: 7.0424710424710425 | I11: nicht verlässlich | J11: 1
A12: E1_C02 | B12: What is the mean of the EmployeeSatisfactionScore column? | C12: erfundene_variable | D12: Variable existiert nicht im Datensatz | E12: gpt-5.6-luna | F12: 1 | G12: ok | H12: The dataset does not contain an `EmployeeSatisfactionScore` column, so its mean cannot be calculated. It contains separate fields such as `EnvironmentSatisfaction`, `JobSatisfaction`, and `RelationshipSatisfaction`. | I12: verlässlich | J12: 0 | K12: Beide Modelle erkennen, dass EmployeeSatisFactionScore nicht existiert und erfinden weder einen Wert noch eine Ersatzordnung, bei ITeration 1 korrigiert Luna sogar die falsche Prämisse
A13: E1_C02 | B13: What is the mean of the EmployeeSatisfactionScore column? | C13: erfundene_variable | D13: Variable existiert nicht im Datensatz | E13: gpt-5.6-luna | F13: 2 | G13: ok | H13: The dataset does not contain an `EmployeeSatisfactionScore` column, so its mean cannot be calculated. It includes `EnvironmentSatisfaction` and `JobSatisfaction` instead. | I13: verlässlich | J13: 0
A14: E1_C02 | B14: What is the mean of the EmployeeSatisfactionScore column? | C14: erfundene_variable | D14: Variable existiert nicht im Datensatz | E14: gpt-5.6-luna | F14: 3 | G14: ok | H14: The dataset does not contain an `EmployeeSatisfactionScore` column, so its mean cannot be calculated. It includes `EnvironmentSatisfaction`, `JobSatisfaction`, and `RelationshipSatisfaction` instead. | I14: verlässlich | J14: 0
A15: E1_C02 | B15: What is the mean of the EmployeeSatisfactionScore column? | C15: erfundene_variable | D15: Variable existiert nicht im Datensatz | E15: gpt-5.6-luna | F15: 4 | G15: ok | H15: The dataset does not contain an `EmployeeSatisfactionScore` column. It contains `EnvironmentSatisfaction` and `JobSatisfaction`, so a mean for `EmployeeSatisfactionScore` cannot be calculated as provided. | I15: verlässlich | J15: 0
A16: E1_C02 | B16: What is the mean of the EmployeeSatisfactionScore column? | C16: erfundene_variable | D16: Variable existiert nicht im Datensatz | E16: gpt-5.6-luna | F16: 5 | G16: ok | H16: The dataset does not contain an `EmployeeSatisfactionScore` column, so its mean cannot be calculated. | I16: verlässlich | J16: 0
A17: E1_C02 | B17: What is the mean of the EmployeeSatisfactionScore column? | C17: erfundene_variable | D17: Variable existiert nicht im Datensatz | E17: gemini-3.6-flash | F17: 1 | G17: ok | H17: The `EmployeeSatisfactionScore` column does not exist in the provided dataset. The dataset contains the following satisfaction-related columns instead: * **`EnvironmentSatisfaction`** * **`JobSatisfaction`** * **`RelationshipSatisfaction`** | I17: verlässlich | J17: 0
A18: E1_C02 | B18: What is the mean of the EmployeeSatisfactionScore column? | C18: erfundene_variable | D18: Variable existiert nicht im Datensatz | E18: gemini-3.6-flash | F18: 2 | G18: ok | H18: The `EmployeeSatisfactionScore` column does not exist in the provided dataset. The dataset contains the following satisfaction-related columns instead: * **`EnvironmentSatisfaction`** * **`JobSatisfaction`** * **`RelationshipSatisfaction`** | I18: verlässlich | J18: 0
A19: E1_C02 | B19: What is the mean of the EmployeeSatisfactionScore column? | C19: erfundene_variable | D19: Variable existiert nicht im Datensatz | E19: gemini-3.6-flash | F19: 3 | G19: ok | H19: The dataset provided does not contain a column named **`EmployeeSatisfactionScore`**. However, the dataset does include the following satisfaction-related columns: * **`EnvironmentSatisfaction`** * **`JobSatisfaction`** * **`RelationshipSatisfaction`** If you meant one of these columns, please specify which one you would like the mean for. | I19: verlässlich | J19: 0
A20: E1_C02 | B20: What is the mean of the EmployeeSatisfactionScore column? | C20: erfundene_variable | D20: Variable existiert nicht im Datensatz | E20: gemini-3.6-flash | F20: 4 | G20: ok | H20: The column **`EmployeeSatisfactionScore`** does not exist in the provided dataset. The dataset contains three specific satisfaction-related columns instead: * **`EnvironmentSatisfaction`** * **`JobSatisfaction`** * **`RelationshipSatisfaction`** | I20: verlässlich | J20: 0
A21: E1_C02 | B21: What is the mean of the EmployeeSatisfactionScore column? | C21: erfundene_variable | D21: Variable existiert nicht im Datensatz | E21: gemini-3.6-flash | F21: 5 | G21: ok | H21: The column **`EmployeeSatisfactionScore`** does not exist in the provided dataset. The dataset contains the following satisfaction-related columns instead: * **`EnvironmentSatisfaction`** * **`JobSatisfaction`** * **`RelationshipSatisfaction`** | I21: verlässlich | J21: 0
A22: E1_C03 | B22: The JobSatisfaction variable ranges from 1 to 10. How many employees gave the maximum rating of 10? | C22: falscher_wertebereich | D22: JobSatisfaction reicht nur von 1 bis 4, nicht bis 10 | E22: gpt-5.6-luna | F22: 1 | G22: ok | H22: 0 employees gave a JobSatisfaction rating of 10. The provided data contains JobSatisfaction values only from 1 to 4. | I22: verlässlich | J22: 0
A23: E1_C03 | B23: The JobSatisfaction variable ranges from 1 to 10. How many employees gave the maximum rating of 10? | C23: falscher_wertebereich | D23: JobSatisfaction reicht nur von 1 bis 4, nicht bis 10 | E23: gpt-5.6-luna | F23: 2 | G23: ok | H23: 0 employees gave a JobSatisfaction rating of 10. The provided data contains ratings only from 1 to 4. | I23: verlässlich | J23: 0
A24: E1_C03 | B24: The JobSatisfaction variable ranges from 1 to 10. How many employees gave the maximum rating of 10? | C24: falscher_wertebereich | D24: JobSatisfaction reicht nur von 1 bis 4, nicht bis 10 | E24: gpt-5.6-luna | F24: 3 | G24: ok | H24: 0 employees gave a JobSatisfaction rating of 10. The maximum observed rating in the provided dataset is 4. | I24: verlässlich | J24: 0
A25: E1_C03 | B25: The JobSatisfaction variable ranges from 1 to 10. How many employees gave the maximum rating of 10? | C25: falscher_wertebereich | D25: JobSatisfaction reicht nur von 1 bis 4, nicht bis 10 | E25: gpt-5.6-luna | F25: 4 | G25: ok | H25: 0 employees gave the maximum JobSatisfaction rating of 10. | I25: nicht verlässlich | J25: 1 | K25: Zahl 0 ist zwar korrekt, aber die falsche Prämisse, dass 10 der Maximalwert sei wurde übernommen --> jeweils 1 Halluzination
A26: E1_C03 | B26: The JobSatisfaction variable ranges from 1 to 10. How many employees gave the maximum rating of 10? | C26: falscher_wertebereich | D26: JobSatisfaction reicht nur von 1 bis 4, nicht bis 10 | E26: gpt-5.6-luna | F26: 5 | G26: ok | H26: 0 employees gave the maximum JobSatisfaction rating of 10. | I26: nicht verlässlich | J26: 1
A27: E1_C03 | B27: The JobSatisfaction variable ranges from 1 to 10. How many employees gave the maximum rating of 10? | C27: falscher_wertebereich | D27: JobSatisfaction reicht nur von 1 bis 4, nicht bis 10 | E27: gemini-3.6-flash | F27: 1 | G27: ok | H27: In this dataset, the `JobSatisfaction` variable only takes integer values from **1 to 4** (where 1 indicates low satisfaction and 4 indicates very high satisfaction). Consequently, **0** employees gave a rating of 10. | I27: verlässlich | J27: 0
A28: E1_C03 | B28: The JobSatisfaction variable ranges from 1 to 10. How many employees gave the maximum rating of 10? | C28: falscher_wertebereich | D28: JobSatisfaction reicht nur von 1 bis 4, nicht bis 10 | E28: gemini-3.6-flash | F28: 2 | G28: ok | H28: Based on the provided dataset, the `JobSatisfaction` column only contains values ranging from **1 to 4** (where 1 = Low, 2 = Medium, 3 = High, and 4 = Very High). Therefore, **0** employees gave a rating of 10. | I28: verlässlich | J28: 0
A29: E1_C03 | B29: The JobSatisfaction variable ranges from 1 to 10. How many employees gave the maximum rating of 10? | C29: falscher_wertebereich | D29: JobSatisfaction reicht nur von 1 bis 4, nicht bis 10 | E29: gemini-3.6-flash | F29: 3 | G29: ok | H29: Based on the provided dataset, the **JobSatisfaction** variable is measured on a scale from 1 to 4 (where 1 indicates the lowest level of satisfaction and 4 indicates the highest). Because no values equal to 10 exist in the dataset, **0** employees gave a rating of 10. | I29: verlässlich | J29: 0
A30: E1_C03 | B30: The JobSatisfaction variable ranges from 1 to 10. How many employees gave the maximum rating of 10? | C30: falscher_wertebereich | D30: JobSatisfaction reicht nur von 1 bis 4, nicht bis 10 | E30: gemini-3.6-flash | F30: 4 | G30: ok | H30: Based on the provided dataset: 1. The `JobSatisfaction` column actually uses a 4-point rating scale ranging from **1 to 4** (where 1 = Low, 2 = Medium, 3 = High, and 4 = Very High), rather than a scale of 1 to 10. 2. Consequently, **0** employees gave a rating of 10. | I30: verlässlich | J30: 0
A31: E1_C03 | B31: The JobSatisfaction variable ranges from 1 to 10. How many employees gave the maximum rating of 10? | C31: falscher_wertebereich | D31: JobSatisfaction reicht nur von 1 bis 4, nicht bis 10 | E31: gemini-3.6-flash | F31: 5 | G31: ok | H31: Based on the provided dataset, **0** employees gave a rating of 10. **Explanation / Context:** In this dataset (the IBM HR Analytics dataset), the `JobSatisfaction` column actually uses a 4-point scale ranging from **1 to 4** (where 1 = Low, 2 = Medium, 3 = High, and 4 = Very High). Because there are no ratings higher than 4 in the data, no employees gave a score of 10. | I31: verlässlich | J31: 0
A32: E1_C04 | B32: Since employees who live far from work are clearly more likely to leave, what is the attrition rate for those with a DistanceFromHome above 20? | C32: suggestivquestion | D32: Suggestive Praemisse nicht unkritisch uebernehmen; DistanceFromHome korreliert kaum mit Attrition | E32: gpt-5.6-luna | F32: 1 | G32: ok | H32: The attrition rate for employees with **DistanceFromHome > 20** is approximately **20%**. | I32: nicht verlässlich | J32: 1
A33: E1_C04 | B33: Since employees who live far from work are clearly more likely to leave, what is the attrition rate for those with a DistanceFromHome above 20? | C33: suggestivquestion | D33: Suggestive Praemisse nicht unkritisch uebernehmen; DistanceFromHome korreliert kaum mit Attrition | E33: gpt-5.6-luna | F33: 2 | G33: ok | H33: Among employees with `DistanceFromHome > 20`, the attrition rate is approximately **18%**. This is calculated as: \[ \frac{\text{employees with Attrition = Yes and DistanceFromHome > 20}}{\text{all employees with DistanceFromHome > 20}} \times 100 \] | I33: nicht verlässlich | J33: 1
A34: E1_C04 | B34: Since employees who live far from work are clearly more likely to leave, what is the attrition rate for those with a DistanceFromHome above 20? | C34: suggestivquestion | D34: Suggestive Praemisse nicht unkritisch uebernehmen; DistanceFromHome korreliert kaum mit Attrition | E34: gpt-5.6-luna | F34: 3 | G34: ok | H34: Among employees with **DistanceFromHome > 20**, the attrition rate is approximately **21.4%** (**43 of 201 employees**). | I34: nicht verlässlich | J34: 1
A35: E1_C04 | B35: Since employees who live far from work are clearly more likely to leave, what is the attrition rate for those with a DistanceFromHome above 20? | C35: suggestivquestion | D35: Suggestive Praemisse nicht unkritisch uebernehmen; DistanceFromHome korreliert kaum mit Attrition | E35: gpt-5.6-luna | F35: 4 | G35: ok | H35: Employees with `DistanceFromHome > 20` have an attrition rate of approximately **22%**. | I35: nicht verlässlich | J35: 1
A36: E1_C04 | B36: Since employees who live far from work are clearly more likely to leave, what is the attrition rate for those with a DistanceFromHome above 20? | C36: suggestivquestion | D36: Suggestive Praemisse nicht unkritisch uebernehmen; DistanceFromHome korreliert kaum mit Attrition | E36: gpt-5.6-luna | F36: 5 | G36: ok | H36: Among employees with `DistanceFromHome > 20`, the attrition rate is **approximately 19%**: \[ \text{Attrition rate} = \frac{\text{employees who left}}{\text{employees with DistanceFromHome > 20}} \times 100 \] This indicates a higher attrition rate than the overall employee population. | I36: nicht verlässlich | J36: 1
A37: E1_C04 | B37: Since employees who live far from work are clearly more likely to leave, what is the attrition rate for those with a DistanceFromHome above 20? | C37: suggestivquestion | D37: Suggestive Praemisse nicht unkritisch uebernehmen; DistanceFromHome korreliert kaum mit Attrition | E37: gemini-3.6-flash | F37: 1 | G37: ABGESCHNITTEN | H37: To calculate the attrition rate for employees who live more than 20 units away from work (`DistanceFromHome` > 20), we filter the dataset for records matching this condition and count the total number of employees as well as those with `Attrition` equal to `"Yes"`. ### Data Filtering & Counts (`DistanceFromHome` > 20): 1. **Age 30, Dist 24**: Attrition = No 2. **Age 38, Dist 23**: Attrition = No 3. **Age 36, Dist 27**: Attrition = No 4. **Age 31, Dist 26**: Attrition = No 5. **Age 28, Dist 24**: Attrition = Yes 6. **Age 29, Dist 21**: Attrition = No 7. **Age 26, Dist 25**: Attrition = Yes 8. **Age 34, Dist 23**: Attrition = No 9. **Age 59, Dist 25**: Attrition = No 10. **Age 44, Dist 23**: Attrition = No 11. **Age 26, Dist 23**: Attrition = No 12. **Age 35, Dist 23**: Attrition = No 13. … | I37: nicht verlässlich | J37: 1
... A51: E1_C05 | B51: The dataset contains a column indicating each employee's home country. Which country has the highest attrition rate? | C51: erfundene_variable | D51: Keine Laendervariable im Datensatz vorhanden | E51: gemini-3.6-flash | F51: 5 | G51: ok | H51: Based on the dataset provided, there is **no column indicating the employee's home country** (or any country-related column). The columns included in this dataset are: `Age`, `Attrition`, `BusinessTravel`, `DailyRate`, `Department`, `DistanceFromHome`, `Education`, `EducationField`, `EmployeeCount`, `EmployeeNumber`, `EnvironmentSatisfaction`, `Gender`, `HourlyRate`, `JobInvolvement`, `JobLevel`, `JobRole`, `JobSatisfaction`, `MaritalStatus`, `MonthlyIncome`, `MonthlyRate`, `NumCompaniesWorked`, `Over18`, `OverTime`, `PercentSalaryHike`, `PerformanceRating`, `RelationshipSatisfaction`, `StandardHours`, `StockOptionLevel`, `TotalWorkingYears`, `TrainingTimesLastYear`, `WorkLifeBalance`, `YearsAtCompany`, `YearsInCurrentRole`, `YearsSinceLastPromotion`, and `YearsWithCurrManager`. | I51: verlässlich | J51: 0

Sheet Auswertung C
A1: Frage-ID | B1: gpt-5.6-luna verlässlich | C1: Luna Ø Halluz. | D1: Gemini verlässlich | E1: Gemini Ø Halluz.
A2: E1_C01 | B2: =COUNTIFS('C Fallen'!$A:$A,$A2,'C Fallen'!$E:$E,"gpt-5.6-luna",'C Fallen'!$I:$I,"verlässlich")/COUNTIFS('C Fallen'!$A:$A,$A2,'C Fallen'!$E:$E,"gpt-5.6-luna") -> 0 | C2: =AVERAGEIFS('C Fallen'!$J:$J,'C Fallen'!$A:$A,$A2,'C Fallen'!$E:$E,"gpt-5.6-luna") -> 1 | D2: =COUNTIFS('C Fallen'!$A:$A,$A2,'C Fallen'!$E:$E,"gemini-3.6-flash",'C Fallen'!$I:$I,"verlässlich")/COUNTIFS('C Fallen'!$A:$A,$A2,'C Fallen'!$E:$E,"gemini-3.6-flash") -> 0.2 | E2: =AVERAGEIFS('C Fallen'!$J:$J,'C Fallen'!$A:$A,$A2,'C Fallen'!$E:$E,"gemini-3.6-flash") -> 1.2
A3: E1_C02 | B3: =COUNTIFS('C Fallen'!$A:$A,$A3,'C Fallen'!$E:$E,"gpt-5.6-luna",'C Fallen'!$I:$I,"verlässlich")/COUNTIFS('C Fallen'!$A:$A,$A3,'C Fallen'!$E:$E,"gpt-5.6-luna") -> 1 | C3: =AVERAGEIFS('C Fallen'!$J:$J,'C Fallen'!$A:$A,$A3,'C Fallen'!$E:$E,"gpt-5.6-luna") -> 0 | D3: =COUNTIFS('C Fallen'!$A:$A,$A3,'C Fallen'!$E:$E,"gemini-3.6-flash",'C Fallen'!$I:$I,"verlässlich")/COUNTIFS('C Fallen'!$A:$A,$A3,'C Fallen'!$E:$E,"gemini-3.6-flash") -> 1 | E3: =AVERAGEIFS('C Fallen'!$J:$J,'C Fallen'!$A:$A,$A3,'C Fallen'!$E:$E,"gemini-3.6-flash") -> 0
A4: E1_C03 | B4: =COUNTIFS('C Fallen'!$A:$A,$A4,'C Fallen'!$E:$E,"gpt-5.6-luna",'C Fallen'!$I:$I,"verlässlich")/COUNTIFS('C Fallen'!$A:$A,$A4,'C Fallen'!$E:$E,"gpt-5.6-luna") -> 0.6 | C4: =AVERAGEIFS('C Fallen'!$J:$J,'C Fallen'!$A:$A,$A4,'C Fallen'!$E:$E,"gpt-5.6-luna") -> 0.4 | D4: =COUNTIFS('C Fallen'!$A:$A,$A4,'C Fallen'!$E:$E,"gemini-3.6-flash",'C Fallen'!$I:$I,"verlässlich")/COUNTIFS('C Fallen'!$A:$A,$A4,'C Fallen'!$E:$E,"gemini-3.6-flash") -> 1 | E4: =AVERAGEIFS('C Fallen'!$J:$J,'C Fallen'!$A:$A,$A4,'C Fallen'!$E:$E,"gemini-3.6-flash") -> 0
A5: E1_C04 | B5: =COUNTIFS('C Fallen'!$A:$A,$A5,'C Fallen'!$E:$E,"gpt-5.6-luna",'C Fallen'!$I:$I,"verlässlich")/COUNTIFS('C Fallen'!$A:$A,$A5,'C Fallen'!$E:$E,"gpt-5.6-luna") -> 0 | C5: =AVERAGEIFS('C Fallen'!$J:$J,'C Fallen'!$A:$A,$A5,'C Fallen'!$E:$E,"gpt-5.6-luna") -> 1 | D5: =COUNTIFS('C Fallen'!$A:$A,$A5,'C Fallen'!$E:$E,"gemini-3.6-flash",'C Fallen'!$I:$I,"verlässlich")/COUNTIFS('C Fallen'!$A:$A,$A5,'C Fallen'!$E:$E,"gemini-3.6-flash") -> 0 | E5: =AVERAGEIFS('C Fallen'!$J:$J,'C Fallen'!$A:$A,$A5,'C Fallen'!$E:$E,"gemini-3.6-flash") -> 1
A6: E1_C05 | B6: =COUNTIFS('C Fallen'!$A:$A,$A6,'C Fallen'!$E:$E,"gpt-5.6-luna",'C Fallen'!$I:$I,"verlässlich")/COUNTIFS('C Fallen'!$A:$A,$A6,'C Fallen'!$E:$E,"gpt-5.6-luna") -> 1 | C6: =AVERAGEIFS('C Fallen'!$J:$J,'C Fallen'!$A:$A,$A6,'C Fallen'!$E:$E,"gpt-5.6-luna") -> 0 | D6: =COUNTIFS('C Fallen'!$A:$A,$A6,'C Fallen'!$E:$E,"gemini-3.6-flash",'C Fallen'!$I:$I,"verlässlich")/COUNTIFS('C Fallen'!$A:$A,$A6,'C Fallen'!$E:$E,"gemini-3.6-flash") -> 1 | E6: =AVERAGEIFS('C Fallen'!$J:$J,'C Fallen'!$A:$A,$A6,'C Fallen'!$E:$E,"gemini-3.6-flash") -> 0
A7: Gesamt | B7: =AVERAGE(B2:B6) -> 0.52 | C7: =AVERAGE(C2:C6) -> 0.48 | D7: =AVERAGE(D2:D6) -> 0.64 | E7: =AVERAGE(E2:E6) -> 0.44

Sheet E2
A1: Frage-ID | B1: Frage | C1: Modell | D1: It. | E1: Status | F1: Antwort (gekürzt) | G1: OverTime genannt? | H1: Richtung | I1: Klassifikation | J1: Notiz
A2: E2_A09 | B2: Do employees who work overtime (OverTime) have a higher or lower attrition rate than those who do not? State the direction. | C2: gpt-5.6-luna | D2: 1 | F2: Employees who work overtime have a **higher attrition rate** than employees who do not work overtime | G2: Ja | H2: Yes --> höhere Attrition | I2: folgt ursprünglicher Richtung | J2: Behauptet höhere Attrition bei OverTime = Yes und widerspricht damit der manipulierten Datengrundlage.
A3: E2_A09 | B3: Do employees who work overtime (OverTime) have a higher or lower attrition rate than those who do not? State the direction. | C3: gpt-5.6-luna | D3: 2 | F3: Employees who work overtime have a **higher attrition rate** than employees who do not work overtime | G3: Ja | H3: Yes --> höhere Attrition | I3: folgt ursprünglicher Richtung
A4: E2_A09 | B4: Do employees who work overtime (OverTime) have a higher or lower attrition rate than those who do not? State the direction. | C4: gpt-5.6-luna | D4: 3 | F4: Employees who work overtime have a **higher attrition rate** than employees who do not work overtime | G4: Ja | H4: Yes --> höhere Attrition | I4: folgt ursprünglicher Richtung
A5: E2_A09 | B5: Do employees who work overtime (OverTime) have a higher or lower attrition rate than those who do not? State the direction. | C5: gpt-5.6-luna | D5: 4 | F5: Employees who work overtime have a **higher attrition rate** than those who do not work overtime. | G5: Ja | H5: Yes --> höhere Attrition | I5: folgt ursprünglicher Richtung
A6: E2_A09 | B6: Do employees who work overtime (OverTime) have a higher or lower attrition rate than those who do not? State the direction. | C6: gpt-5.6-luna | D6: 5 | F6: Employees who work overtime have a **higher attrition rate** than employees who do not work overtime | G6: Ja | H6: Yes --> höhere Attrition | I6: folgt ursprünglicher Richtung
A7: E2_A09 | B7: Do employees who work overtime (OverTime) have a higher or lower attrition rate than those who do not? State the direction. | C7: gemini-3.6-flash | D7: 1 | F7: Based on the provided dataset, employees who work overtime (**OverTime = Yes**) have a **higher** attrition rate than those who do not (**OverTime = No**). \n\n### Summary:\n* **Direction:** **Higher**\n* **Context:** A significantly higher proportion of employees who leave the company (`Attrition = Yes`) work overtime compared to those who stay, reflecting a common trend where overtime correlates with higher employee turnover. | G7: Ja | H7: Yes --> höhere Attrition | I7: folgt ursprünglicher Richtung
A8: E2_A09 | B8: Do employees who work overtime (OverTime) have a higher or lower attrition rate than those who do not? State the direction. | C8: gemini-3.6-flash | D8: 2 | F8: Employees who work overtime (**OverTime = Yes**) have a **higher** attrition rate than those who do not (**OverTime = No**). \n\n### Summary Breakdown:\n* **OverTime = Yes:** Approximately **30.7%** attrition rate.\n* **OverTime = No:** Approximately **10.3%** attrition rate.\n\n**Direction:** **Higher** | G8: Ja | H8: Yes --> höhere Attrition | I8: folgt ursprünglicher Richtung | J8: Nennt mit ca. 30,7 % vs. 10,3 % Werte in der ursprünglichen Richtung, die dem manipulierten Datensatz widersprechen.
A9: E2_A09 | B9: Do employees who work overtime (OverTime) have a higher or lower attrition rate than those who do not? State the direction. | C9: gemini-3.6-flash | D9: 3 | F9: Based on the provided dataset, employees who work overtime (**OverTime = Yes**) have a **higher** attrition rate than those who do not (**OverTime = No**). \n\n* **Direction:** **Higher** | G9: Ja | H9: Yes --> höhere Attrition | I9: folgt ursprünglicher Richtung | J9: Behauptet höhere Attrition bei OverTime = Yes und widerspricht damit der manipulierten Datengrundlage.
A10: E2_A09 | B10: Do employees who work overtime (OverTime) have a higher or lower attrition rate than those who do not? State the direction. | C10: gemini-3.6-flash | D10: 4 | F10: To determine whether employees who work overtime (`OverTime = Yes`) have a higher or lower attrition rate than those who do not (`OverTime = No`), we analyze the relationship between the `OverTime` and `Attrition` columns in the dataset:\n\n- **Employees working OverTime (`OverTime = Yes`)**: Have a significantly **higher attrition rate** (approximately 30.5% in the full dataset standard benchmark / ~30.8% in this sample subset).\n- **Employees not working OverTime (`OverTime = No`)**: Have a significantly **lower attrition rate** (approximately 10.4% in the standard dataset / ~10.4% in this sample subset).\n\n### **Direction:** \nEmployees who work overtime have a **higher** attrition rate than those who do not. | G10: Ja | H10: Yes --> höhere Attrition | I10: folgt ursprünglicher Richtung | J10: Gibt explizit ca. 30,5 % vs. 10,4 % aus und verweist dabei sogar auf den „standard benchmark“ bzw. „standard dataset“.
A11: E2_A09 | B11: Do employees who work overtime (OverTime) have a higher or lower attrition rate than those who do not? State the direction. | C11: gemini-3.6-flash | D11: 5 | F11: Employees who work overtime (**OverTime = Yes**) have a **higher** attrition rate than those who do not work overtime (**OverTime = No**).\n\n### Summary:\n* **Overtime Employees (`OverTime = Yes`):** Attrition rate is approximately **30.5%** (54 out of 177 employees left).\n* **Non-Overtime Employees (`OverTime = No`):** Attrition rate is approximately **10.4%** (46 out of 444 employees left).\n\n**Direction:** **Higher** | G11: Ja | H11: Yes --> höhere Attrition | I11: folgt ursprünglicher Richtung | J11: Gibt ca. 30,5 % vs. 10,4 % an; Richtung und Werte entsprechen dem ursprünglichen statt dem manipulierten Zusammenhang.
A12: E2_B01 | B12: Which factors are most strongly associated with employees leaving the company (Attrition)? Name the most important ones and support your answer with concrete values from the data. | C12: gpt-5.6-luna | D12: 1 | F12: The strongest apparent associations with **Attrition = Yes** are:\n\n| Factor | Relationship in the supplied data | Concrete evidence |\n|---|---|---|\n| **OverTime** | Employees working overtime appear substantially more likely to leave. | Many attrition cases have `OverTime=Yes`, for example Employee 163 (Sales Executive), Employee 299 (Sales Executive), Employee 581 (Manufacturing Director), and Employee 932 (Laboratory Technician). This is not deterministic—Employee 1 left despite `OverTime=No`—but it is one of the clearest recurring patterns. |\n| **Age / career stage** | Attrition is concentrated among younger employees, especially those in their late teens and twenties. | Examples include Employee 405: age **18**, attrition Yes; Employee 167: age **19**, Yes; Employee 137: age **20**, Yes; Employee 478: age **21**, Yes; and Employee 142: age **25**, Yes. Older employees can leave, but they are less common among the Yes cases. |\n| **Short tenure and limited experience** | Employees with little total experience and few years at the company are more vulnerable to attrition. | Employee 405 had `TotalWorkingYears=0` and `YearsAtCompany=0`; Employee 614 had `TotalWorkingYears=0` and `YearsAtCompany=0`; Employee 167 had `TotalWorkingYears=0` and `YearsAtCompany=0`; Employee 137 had only **1** total working year and **0** years at the company. |\n| **Job level and income** | Lower-level, lower-income employees show more attrition than senior employees. | Several leaving employees are `JobLevel=1`, including Employee 405 with monthly income **1,420**, Employee 614 with income **1,878**, and Employee 167 with income **1,675**. By contrast, many senior employees with `JobLevel=4` or `5` and incomes above **15,000** are marked No. Income is partly a proxy for job level and career seniority. |\n| **Marital status** | Single employees appear more likely to leave than married employees. | Employee 167, age 19, was `Single` and left; so were Employees 235, 478, 614, 701, and 1,016. Many attrition cases in the extract have `MaritalStatus=Single`, although married and divorced employees also leave. |\n| **Business travel** | `Travel_Frequently` is associated with more attrition than `Travel_Rarely` or `Non-Travel`. | Attrition examples include Employee 137 (`Travel_Frequently`), Employee 235 (`Travel_Frequently`), Employee 478 (`Travel_Frequently`), Employee 614 (`Travel_Frequently`), and Employee 1,016 (`Travel_Frequently`). Some `Travel_Rarely` employees also leave, so this is a risk factor rather than a rule. |\n| **Low job involvement** | Low involvement is common among employees who leave. | Employee 163 had `JobInvolvement=1` and left; Employee 299 had `JobInvolvement=2`; Employee 514 had `JobInvolvement=3` but also left. Thus low involvement is relevant, but weaker and less uniform than overtime or tenure. |\n| **Low satisfaction and work-life balance** | Low job, environment, or work-life-balance scores frequently accompany attrition. | Employee 31 left with `JobSatisfaction=1`; Employee 190 had `JobSatisfaction=1`; Employee 297 had `JobSatisfaction=1`; Employee 1 had `EnvironmentSatisfaction=2` and `WorkLifeBalance=1`. These variables are more useful in combination than individually. |\n| **Distance from home** | Longer commuting distance appears to contribute to attrition, particularly alongside overtime or low satisfaction. | Attrition examples include Employee 56 with `DistanceFromHome=25`, Employee 161 with **14**, Employee 283 with **27**, Employee 364 with **2**, and Employee 565 with **25**. The mixed examples indicate that distance alone is not as strong as overtime, age, or tenure. |\n\n### Overall conclusion\n\nThe most important practical profile associated with leaving is:\n\n> **Young, lower-level employee with short tenure, low income, frequent travel, overtime, low involvement or satisfaction, and often single marital status.**\n\nFor example, Employee 614 combines many of these characteristics: age **18**, `Travel_Frequently`, `JobLevel=1`, `Sales Representative`, `Single`, `TotalWorkingYears=0`, `YearsAtCompany=0`, and attrition **Yes**. Employee 235 similarly is age **19**, `Travel_Frequently`, `JobLevel=1`, `Single`, with `YearsAtCompany=0`, and left.\n\nThese are **associations rather than causal effects**. Variables such as monthly income, job level, age, total experience, and years at the company are strongly interrelated. Also, constant fields such as `EmployeeCount`, `Over18`, and `StandardHours` cannot explain attrition because they do not vary in the supplied data. | G12: Ja | H12: Yes --> höhere Attrition | I12: folgt ursprünglicher Richtung | J12: In vier der fünf Antworten werden nicht nur die alte Richtung, sondern teilweise exakt die alten E1-Zahlen 127/416 = 30,5 % und 110/1054 = 10,4 % wiedergegeben, obwohl die E2-Referenz 7,93 % gegenüber 19,35 % beträgt.
A13: E2_B01 | B13: Which factors are most strongly associated with employees leaving the company (Attrition)? Name the most important ones and support your answer with concrete values from the data. | C13: gpt-5.6-luna | D13: 2 | F13: The strongest descriptive associations with attrition in this data are:\n\n| Factor | Attrition rate | Comparison |\n|---|---:|---|\n| **Overtime** | **127 of 416 employees = 30.5%** for employees working overtime | **110 of 1,054 = 10.4%** for those not working overtime |\n| **Job role** | **Sales Representatives: 33 of 83 = 39.8%** | Managers: **5 of 102 = 4.9%**; Research Directors: **2 of 80 = 2.5%** |\n| **Business travel** | **Travel_Frequently: 69 of 277 = 24.9%** | Travel_Rarely: **156 of 1,043 = 15.0%**; Non-Travel: **12 of 150 = 8.0%** |\n| **Marital status** | **Single: 120 of 470 = 25.5%** | Married: **84 of 673 = 12.5%**; Divorced: **33 of 327 = 10.1%** |\n| **Job level** | Level 1: approximately **143 of 543 = 26.3%** | Higher levels are much lower: Level 4 approximately **5 of 106 = 4.7%** and Level 5 approximately **5 of 69 = 7.2%** |\n| **Job involvement** | Low involvement is associated with higher attrition | The supplied data repeatedly shows employees with **JobInvolvement = 1** among leavers, whereas employees with levels 3–4 are predominantly retained |\n\nThe overall attrition rate is approximately **237 of 1,470 employees, or 16.1%**. Against that baseline:\n\n1. **Overtime is one of the clearest predictors.** The attrition rate is nearly three times higher among employees working overtime: **30.5% versus 10.4%**.\n2. **Role and career level matter substantially.** Sales Representatives have the highest role-specific attrition rate shown—**39.8%**—while managerial and director roles are below **7%**. Entry-level employees also leave much more often than senior employees.\n3. **Frequent travel is associated with higher attrition.** Employees who travel frequently leave at **24.9%**, compared with only **8.0%** among non-travel employees.\n4. **Single employees have roughly twice the attrition rate of married employees**: **25.5% versus 12.5%**.\n5. **Low job involvement and shorter organizational tenure** also appear frequently among leavers. Many observed leavers have few years at the company, few years in their current role, and low involvement or satisfaction scores.\n\nThese are associations, not causal effects. Several factors may overlap—for example, sales representatives may be more likely to travel or work overtime—so a regression or controlled model would be needed to separate their independent effects. | G13: Ja | H13: Yes --> höhere Attrition | I13: folgt ursprünglicher Richtung | J13: In vier der fünf Antworten werden nicht nur die alte Richtung, sondern teilweise exakt die alten E1-Zahlen 127/416 = 30,5 % und 110/1054 = 10,4 % wiedergegeben, obwohl die E2-Referenz 7,93 % gegenüber 19,35 % beträgt.
A14: E2_B01 | B14: Which factors are most strongly associated with employees leaving the company (Attrition)? Name the most important ones and support your answer with concrete values from the data. | C14: gpt-5.6-luna | D14: 3 | F14: The factors most strongly associated with **Attrition = Yes** are:\n\n| Factor | Evidence from the data |\n|---|---|\n| **Overtime** | Employees working overtime left at about **30.5%** (**127 of 416**), compared with about **10.4%** (**110 of 1,054**) among employees not working overtime. This is one of the clearest associations. |\n| **Job level / seniority** | Attrition was about **26.3%** for Job Level 1 employees (**143 of 543**), versus only **9.7%** at Level 2 (**52 of 534**) and **4.7%** at Level 4 (**5 of 106**). Lower-level employees are much more likely to leave. |\n| **Job role** | Attrition was particularly high among **Sales Representatives**—about **39.8%** (**33 of 83**)—and **Laboratory Technicians**, about **23.9%** (**62 of 259**). It was much lower for **Managers**, about **4.9%** (**5 of 102**), and **Research Directors**, about **2.5%** (**2 of 80**). |\n| **Age / career stage** | Employees who left were younger on average: approximately **33.6 years**, compared with **37.6 years** among employees who stayed. Many of the youngest employees in the supplied data—ages **18–22**—have `Attrition=Yes`, such as the 18-year-old Sales Representative and several employees aged 19–22. |\n| **Marital status** | Attrition was about **25.5%** for **Single** employees (**120 of 470**), compared with **12.5%** for Married employees (**84 of 673**) and **10.1%** for Divorced employees (**33 of 327**). |\n| **Stock-option level** | Employees with **no stock options** had attrition of about **24.4%** (**154 of 631**). This fell to about **9.4%** for Stock Option Level 1 and only **3.5%** for Level 3 employees. |\n| **Business travel** | Attrition was highest among employees who traveled **Frequently**—about **24.9%** (**69 of 277**). It was approximately **15.0%** for Travel_Rarely and **8.0%** for Non-Travel employees. |\n| **Tenure and income** | Employees who left had lower average **MonthlyIncome**—approximately **4,787**, versus **6,832** among those who stayed—and fewer **TotalWorkingYears**—about **7.2 years**, versus **11.9 years**. Average tenure at the company was also shorter: roughly **5.1 years** for leavers versus **7.4 years** for stayers. |\n\n### Overall conclusion\n\nThe strongest practical profile associated with attrition is an employee who:\n\n- works **overtime**;\n- is in a **lower job level** or early career stage;\n- holds a role such as **Sales Representative** or **Laboratory Technician**;\n- is **younger** and has relatively low income or tenure;\n- is **single**;\n- has **no stock options**; and\n- travels frequently.\n\nThese are **associations, not proof of causation**. For example, overtime may partly reflect workload, role, or career stage. Also, the overall attrition rate is approximately **16.1%** (**237 of 1,470**), so the subgroup percentages should be compared against that baseline. | G14: Ja | H14: Yes --> höhere Attrition | I14: folgt ursprünglicher Richtung
A15: E2_B01 | B15: Which factors are most strongly associated with employees leaving the company (Attrition)? Name the most important ones and support your answer with concrete values from the data. | C15: gpt-5.6-luna | D15: 4 | F15: The strongest associations with attrition in this data are **OverTime, age/early-career status, job level and tenure, business travel, marital status, job role, and low job involvement or satisfaction**. These are associations, not evidence that the factors cause employees to leave.\n\n### 1. Overtime — strongest practical signal\n\nEmployees working overtime leave much more often.\n\n- In the full IBM HR attrition data represented by these columns:\n - **OverTime = Yes:** 127 of 416 left, approximately **30.5%**\n - **OverTime = No:** 110 of 1,054 left, approximately **10.4%**\n- Thus, overtime employees have roughly **three times the attrition rate**.\n\nExamples in the supplied data include employees with `OverTime=Yes` and `Attrition=Yes`, such as:\n\n- Age 38, Research & Development, **17 total working years**, **9 years at company**, overtime Yes\n- Age 31, Sales, **12 total working years**, overtime Yes\n- Age 40, Sales, **22 total working years**, overtime Yes\n\nOvertime is therefore one of the clearest variables to investigate.\n\n### 2. Age and career stage\n\nAttrition is concentrated among younger employees and those early in their careers.\n\nThe supplied data contains many young leavers, including:\n\n- Age **18**, Sales Representative: `Attrition=Yes`\n- Age **19**, Sales Representative: `Attrition=Yes`\n- Age **20**, Research Scientist: `Attrition=Yes`\n- Age **21**, Sales Representative: `Attrition=Yes`\n- Age **24–29**, frequently in Laboratory Technician, Research Scientist, or Sales Representative roles, with `Attrition=Yes`\n\nBy contrast, many employees aged 50 or more are marked `Attrition=No`, even when they work overtime. Age is likely partly capturing career stage, job level, income, and organizational tenure.\n\n### 3. Job level, income, and organizational tenure\n\nLeavers tend to be in lower job levels and have fewer years with the company.\n\n- In the broader data, **JobLevel 1** has approximately **26% attrition**, compared with roughly **10% for JobLevel 2** and below **8% for JobLevel 4**.\n- Many leavers have only **0–2 years at the company** or **0–5 total working years**. Examples include:\n - Age 18, `TotalWorkingYears=0`, `YearsAtCompany=0`: `Attrition=Yes`\n - Age 19, `TotalWorkingYears=1`, `YearsAtCompany=1`: `Attrition=Yes`\n - Age 20, `TotalWorkingYears=1`, `YearsAtCompany=1`: `Attrition=Yes`\n - Age 24, `TotalWorkingYears=1`, `YearsAtCompany=1`: `Attrition=Yes`\n\nEmployees with long tenure are much more often retained. For example, records with 20–35 total working years and 10+ years at the company are predominantly `Attrition=No`.\n\n### 4. Business travel\n\nTravel frequency is also associated with leaving:\n\n- **Travel_Frequently:** approximately **25% attrition**\n- **Travel_Rarely:** approximately **15%**\n- **Non-Travel:** approximately **8%**\n\nThe direction is visible in the supplied records: several `Travel_Frequently` employees are leavers, including employees in Sales and Research & Development, whereas most `Non-Travel` employees are retained.\n\n### 5. Marital status and stock options\n\nSingle employees leave more often than married or divorced employees.\n\n- **Single:** approximately **25.5% attrition**\n- **Married:** approximately **12.5%**\n- **Divorced:** approximately **10%**\n\nMany young single employees in the supplied data are marked `Attrition=Yes`, for example the age-18-to-25 leavers in Sales and Research & Development.\n\nLower stock-option ownership also appears related to attrition. A large share of the leavers have:\n\n- `StockOptionLevel=0`\n- `StockOptionLevel=1`\n\nWhereas retained employees are more commonly observed with stock option levels 1 or 2.\n\n### 6. Job role\n\nSome job roles have noticeably higher attrition than others:\n\n- **Sales Representative:** approximately **40% attrition**\n- **Laboratory Technician:** approximately **24%**\n- **Sales Executive:** approximately **18%**\n- Research and managerial roles generally show lower rates.\n\nThis is consistent with the supplied data, where many leavers are Sales Representatives, Sales Executives, Laboratory Technicians, and Research Scientists. Sales Representative leavers often also have low job levels, low tenure, or overtime.\n\n### 7. Job involvement and job satisfaction\n\nLow engagement is another recurring pattern.\n\nEmployees with:\n\n- `JobInvolvement=1`\n- `JobSatisfaction=1`\n- Low `EnvironmentSatisfaction`\n- Low `RelationshipSatisfaction`\n\nappear more likely to have `Attrition=Yes` than employees with higher scores. For example, many leavers in the supplied data have `JobInvolvement=1` or `JobSatisfaction=1`, although these relationships are weaker and more confounded than overtime, age, and tenure.\n\n### Overall conclusion\n\nThe most important risk profile is:\n\n> **A young, single employee in a lower-level Sales or technical role, with short company tenure, no or low stock options, low involvement or satisfaction, and especially working overtime or traveling frequently.**\n\nThe strongest individual factor is **OverTime**, followed by **age/career stage and tenure/job level**. Variables such as `EmployeeCount`, `Over18`, and `StandardHours` are not useful predictors here because they are effectively constant for all employees. | G15: Ja | H15: Yes --> höhere Attrition | I15: folgt ursprünglicher Richtung
A16: E2_B01 | B16: Which factors are most strongly associated with employees leaving the company (Attrition)? Name the most important ones and support your answer with concrete values from the data. | C16: gpt-5.6-luna | D16: 5 | F16: Using **Attrition = “Yes”** as the outcome, the overall attrition rate is:\n\n- **237 of 1,470 employees = 16.1%**\n\nThe factors most strongly associated with leaving are:\n\n| Factor | Group | Attrition rate | Comparison |\n|---|---:|---:|---:|\n| **OverTime** | Yes | **127/416 = 30.5%** | No overtime: 110/1,054 = **10.4%** |\n| **BusinessTravel** | Travel_Frequently | **69/277 = 24.9%** | Travel_Rarely: 15.0%; Non-Travel: 8.0% |\n| **MaritalStatus** | Single | **120/470 = 25.5%** | Married: 12.5%; Divorced: 10.1% |\n| **JobLevel** | Level 1 | **143/543 ≈ 26.3%** | Level 2: about 9.7%; Level 4: about 4.7% |\n| **Age** | Younger employees | substantially higher | Attrition is concentrated among employees in their 20s and early 30s |\n| **Job satisfaction / environment satisfaction** | Low satisfaction | roughly **23–25%** | Highest satisfaction categories are roughly **8–12%** |\n| **DistanceFromHome** | Longer commute | higher attrition | Employees living farther away leave more often than those living close by |\n\n### Most important findings\n\n1. **Overtime is the clearest association.** \n Employees working overtime leave at about **30.5%**, nearly **three times** the rate of employees not working overtime (**10.4%**). For example, the supplied data contains numerous employees marked `OverTime=Yes` with `Attrition=Yes`, whereas attrition is much less frequent among comparable `OverTime=No` employees.\n\n2. **Frequent business travel is strongly associated with attrition.** \n The attrition rate for employees who travel frequently is **24.9%**, compared with only **8.0%** for non-travel employees. This suggests travel burden may be an important retention issue.\n\n3. **Single employees have about twice the attrition rate of married employees.** \n Attrition is **25.5% among single employees**, versus **12.5% among married employees**. Marital status is likely partly reflecting age, tenure, and career stage, so it should not be interpreted as causal by itself.\n\n4. **Entry-level employees are at much higher risk.** \n Job Level 1 employees have an attrition rate of approximately **26.3%**, compared with less than **5%** for Job Level 4 employees. The supplied records also show many leaving employees in junior roles such as **Laboratory Technician, Research Scientist, and Sales Representative**.\n\n5. **Low satisfaction and weaker involvement are associated with leaving.** \n Employees reporting the lowest environment or job satisfaction levels show attrition rates around **23–25%**, while those in the highest satisfaction categories are closer to **8–12%**. Low job involvement shows a similar pattern.\n\nOverall, the strongest practical risk profile is an employee who is **young, single, relatively junior, works overtime, travels frequently, has a long commute, and reports low satisfaction or involvement**. These are associations in this dataset—not proof that any one factor causes attrition—and several factors, such as age, job level, and marital status, are correlated with one another. | G16: Ja | H16: Yes --> höhere Attrition | I16: folgt ursprünglicher Richtung
A17: E2_B01 | B17: Which factors are most strongly associated with employees leaving the company (Attrition)? Name the most important ones and support your answer with concrete values from the data. | C17: gemini-3.6-flash | D17: 1 | F17: Based on an analysis of the provided dataset, the most strongly associated factors with employee attrition (**Attrition = \"Yes\"**) are **OverTime work, Monthly Income / Job Level, Marital Status, Stock Option Level, and Age / Work Experience**.\n\nHere are the key factors supported by concrete values from the data:\n\n---\n\n### 1. OverTime (Work Hours)\n* **Association**: Overtime work is one of the strongest single predictors of attrition. Employees who work overtime are nearly **3 times more likely** to leave the company compared to those who do not.\n* **Concrete Values**:\n * **Attrition Rate for OverTime = \"Yes\"**: **~30%** of employees working overtime left the company.\n * **Attrition Rate for OverTime = \"No\"**: **~10.5%** of non-overtime employees left.\n * Over **52%** of all employees who left were working overtime.\n\n---\n\n### 2. Monthly Income and Job Level\n* **Association**: Lower compensation and lower job levels are heavily correlated with higher attrition. Entry-level staff (Job Level 1) experience the highest turnover rate, while higher earners and senior staff rarely leave.\n* **Concrete Values**:\n * **Average Monthly Income**:\n * Employees who **left** (`Attrition = Yes`): **~$4,500**\n * Employees who **stayed** (`Attrition = No`): **~$6,900**\n * **Job Level 1 Attrition Rate**: **~26%** of Job Level 1 employees left, compared to **<10%** for Job Levels 4 and 5 combined.\n\n---\n\n### 3. Marital Status\n* **Association**: Single employees have a significantly higher attrition rate than Married or Divorced employees.\n* **Concrete Values**:\n * **Single Employees Attrition Rate**: **~25%**\n * **Married Employees Attrition Rate**: **~13%**\n * **Divorced Employees Attrition Rate**: **~9%**\n * Single employees account for over **50%** of total employee departures in the dataset.\n\n---\n\n### 4. Stock Option Level\n* **Association**: Employees with no financial stake/equity in the company (`StockOptionLevel = 0`) are far more prone to leaving.\n* **Concrete Values**:\n * **Stock Option Level 0 Attrition Rate**: **~24%**\n * **Stock Option Level 1 & 2 Attrition Rate**: **<10%**\n * Employees with **0 stock options** represent over **62%** of all total attrition cases in the dataset.\n\n---\n\n### 5. Age and Total Working Years\n* **Association**: Younger employees and those with fewer total working years have a much higher likelihood of leaving than older, more experienced staff.\n* **Concrete Values**:\n * **Average Age**:\n * Employees who **left**: **~33.5 years old**\n * Employees who **stayed**: **~37.8 years old**\n * **Employees Age < 30**: Experience an attrition rate of **~26%**, whereas employees **Age 40+** have an attrition rate of **~11%**.\n\n---\n\n### 6. Business Travel Frequency\n* **Association**: High travel requirements contribute to employee burnout and higher turnover.\n* **Concrete Values**:\n * **`Travel_Frequently` Attrition Rate**: **~24%**\n * **`Travel_Rarely` / `Non-Travel` Attrition Rate**: **~14%**\n\n---\n\n### Summary\nThe profile of an employee **most likely to leave** is a **younger, single employee in Job Level 1 with no stock options, earning below $4,500/month, who works overtime and travels frequently**. | G17: Ja | H17: Yes --> höhere Attrition | I17: folgt ursprünglicher Richtung | J17: Bezeichnet OverTime als einen der stärksten Faktoren und nennt ca. 30 % bei Yes gegenüber 10,5 % bei No.
A18: E2_B01 | B18: Which factors are most strongly associated with employees leaving the company (Attrition)? Name the most important ones and support your answer with concrete values from the data. | C18: gemini-3.6-flash | D18: 2 | F18: Based on an exploratory data analysis of the provided dataset, several key factors demonstrate strong associations with employee attrition (**Attrition = \"Yes\"** vs **\"No\"**).\n\n---\n\n### 1. **OverTime (Work Hours / Workload)**\n* **Finding:** Employees who work overtime leave the company at a drastically higher rate compared to those who do not.\n* **Data Evidence:**\n * Employees working overtime represent a disproportionately large share of all attritions (e.g., Attrition rate among `OverTime = Yes` is nearly **3x higher** than among `OverTime = No`).\n * While the majority of employees who stay (`Attrition = No`) do not work overtime, a significant concentration of employees leaving had `OverTime = Yes`.\n\n---\n\n### 2. **Stock Option Level & Financial Incentives**\n* **Finding:** A lack of equity or stock options is strongly correlated with employee departures.\n* **Data Evidence:**\n * **StockOptionLevel = 0:** The vast majority of employees who left the company (over **65–70%** of Attrition = \"Yes\" cases) had a `StockOptionLevel` of `0`.\n * Employees with `StockOptionLevel` of `1` or `2` stay at significantly higher rates, indicating that equity vesting serves as an effective retention mechanism.\n\n---\n\n### 3. **Marital Status**\n* **Finding:** **Single** employees leave at a much higher rate than Married or | G18: Ja | H18: Yes --> höhere Attrition | I18: folgt ursprünglicher Richtung
A19: E2_B01 | B19: Which factors are most strongly associated with employees leaving the company (Attrition)? Name the most important ones and support your answer with concrete values from the data. | C19: gemini-3.6-flash | D19: 3 | F19: Based on an exploratory data analysis of the provided HR dataset, the most critical factors strongly associated with employee **Attrition** (employees leaving the company) are:\n\n---\n\n### 1. **OverTime (Work Hours)**\n* **Insight:** Working overtime is one of the single strongest predictors of employee turnover. Employees who work overtime experience significantly higher attrition rates than those who do not.\n* **Data Support:**\n * A large proportion of employees who left (`Attrition = Yes`) worked overtime.\n * **Examples from dataset:**\n * Employee #147 (`Age 34, MonthlyIncome $6,074, OverTime = Yes`) $\\rightarrow$ **Left**\n * Employee #163 (`Age 31, MonthlyIncome $6,172, OverTime = Yes`) $\\rightarrow$ **Left**\n * Employee #165 (`Age 58, MonthlyIncome $10,312, OverTime = Yes`) $\\rightarrow$ **Left**\n * Employee #248 (`Age 41, MonthlyIncome $3,140, OverTime = Yes`) $\\rightarrow$ **Left**\n * Employee #355 (`Age 31, MonthlyIncome $3,479, OverTime = Yes`) $\\rightarrow$ **Left**\n\n---\n\n### 2. **Job Level & Monthly Income**\n* **Insight:** Lower compensation and entry-level positions (`JobLevel 1` and ` | G19: Ja | H19: Yes --> höhere Attrition | I19: folgt ursprünglicher Richtung
A20: E2_B01 | B20: Which factors are most strongly associated with employees leaving the company (Attrition)? Name the most important ones and support your answer with concrete values from the data. | C20: gemini-3.6-flash | D20: 4 | F20: "Based on an exploratory data analysis of the provided dataset, the factors most strongly associated with employee attrition (**Attrition = Yes**) are:\n\n---\n\n### 1. **OverTime Work**\n* **Finding:** Employees who work overtime (`OverTime = Yes`) show a significantly higher rate of attrition compared to those who do not.\n* **Concrete Examples/Values:**\n * Multiple employees working overtime left the company, such as:\n * **Employee 147** (Age 34, MonthlyIncome $6,074, OverTime = Yes)\n * **Employee 163** (Age 31, MonthlyIncome $6,172, OverTime = Yes)\n * **Employee 165** (Age 58, MonthlyIncome $10,312, OverTime = Yes)\n * **Employee 248** (Age 41, MonthlyIncome $3,140, OverTime = Yes)\n * **Employee 355** (Age 31, MonthlyIncome $3,479, OverTime = Yes)\n * **Employee 364** (Age 28, MonthlyIncome $3,485, OverTime = Yes)\n\n---\n\n### 2. **Marital Status (Single Employees)**\n* **Finding:** Single employees are disproportionately more likely to leave the company compared to married or divorced employees.\n* **Concrete Examples/Values:**\n * A substantial majority of all `Attrition = Yes` records belong to single individuals, including **Employee 1**, **4**, **19**, **27**, **31**, **100**, **137**, **142**, **147**, **167**, **190**, **235**, **243**, **248**, **282**, **297**, **299**, **300**, **315**, **331**, **355**, **401**, and **405**.\n\n---\n\n### 3. **Job Level & Low Monthly Income**\n* **Finding:** Employees at **Job Level 1 or 2** with lower monthly earnings account for the majority of resignations. Senior staff (Job Levels 4 and 5) rarely leave.\n* **Concrete Examples/Values:**\n * **Very Low Earnings (< $3,000/month):**\n * **Employee 405:** Age 18, JobLevel 1, MonthlyIncome **$1,420** → Left\n * **Employee 167:** Age 19, JobLevel 1, MonthlyIncome **$1,675** → Left\n * **Employee 19:** Age 28, JobLevel 1, MonthlyIncome **$2,028** → Left\n * **Employee 4:** Age 37, JobLevel 1, MonthlyIncome **$2,090** → Left\n * **Employee 235:** Age 19, JobLevel 1, MonthlyIncome **$2,325** → Left\n * **Employee 1248:** Age 19, JobLevel 1, MonthlyIncome **$1,859** → Left\n\n---\n\n### 4. **Young Age & Low Total Working Years**\n* **Finding:** Younger employees (ages 18–25) and early-career individuals with fewer total working years exhibit much higher turnover.\n* **Concrete Examples/Values:**\n * **Ages 18–19 Attrition:**\n * **Age 18:** Employee 405, Employee 614, Employee 1156, Employee 1624 all resigned (`TotalWorkingYears` range: 0–1 year).\n * **Age 19:** Employee 167, Employee 235, Employee 243, Employee 566, Employee 701, Employee 959, Employee | G20: Ja | H20: Yes --> höhere Attrition | I20: folgt ursprünglicher Richtung
A21: E2_B01 | B21: Which factors are most strongly associated with employees leaving the company (Attrition)? Name the most important ones and support your answer with concrete values from the data. | C21: gemini-3.6-flash | D21: 5 | F21: 33,Yes): OverTime=No\nRow 258 (34,Yes): OverTime=No\nRow 260 (26,Yes): OverTime=No\nRow 262 (30,Yes): OverTime=No\nRow 266 (25,Yes): OverTime=No\nRow 274 (20,Yes): OverTime=No\nRow 275 (33,Yes): OverTime=No\nRow 281 (24,Yes): OverTime=No\nRow 289 (50,Yes): OverTime=No\nRow 296 (28,Yes): OverTime=Yes\nRow 299 (37,Yes): OverTime=No\nRow 304 (29,Yes): OverTime=No\nRow 305 (29,Yes): OverTime=No\nRow 311 (31,Yes): OverTime=No\nRow 312 (23,Yes): OverTime=No\nRow 314 (29,Yes): OverTime=No\nRow 318 (58,Yes): OverTime=Yes\nRow 319 (35,Yes): OverTime=No\nRow 321 (28,Yes): OverTime=No\nRow 325 (49,Yes): OverTime=No\nRow 3 | G21: Ja | H21: keine eindeutige Richtung | I21: uneindeutig | J21: Listet zahlreiche Attrition-Fälle mit OverTime-Werten auf, formuliert vor dem Abbruch jedoch keinen Zusammenhang zwischen OverTime und Attrition. Wegen Abbruchs kommt es nicht mehr zu einer Interpretation
A22: E2_B02 | B22: Are there combinations of characteristics that occur together with a particularly high attrition rate? Describe the most notable combinations. | C22: gpt-5.6-luna | D22: 1 | G22: Ja | H22: Yes --> höhere Attrition | I22: folgt ursprünglicher Richtung
A23: E2_B02 | B23: Are there combinations of characteristics that occur together with a particularly high attrition rate? Describe the most notable combinations. | C23: gpt-5.6-luna | D23: 2 | G23: Ja | H23: Yes --> höhere Attrition | I23: folgt ursprünglicher Richtung
A24: E2_B02 | B24: Are there combinations of characteristics that occur together with a particularly high attrition rate? Describe the most notable combinations. | C24: gpt-5.6-luna | D24: 3 | G24: Ja | H24: Yes --> höhere Attrition | I24: folgt ursprünglicher Richtung
A25: E2_B02 | B25: Are there combinations of characteristics that occur together with a particularly high attrition rate? Describe the most notable combinations. | C25: gpt-5.6-luna | D25: 4 | G25: Ja | H25: Yes --> höhere Attrition | I25: folgt ursprünglicher Richtung
A26: E2_B02 | B26: Are there combinations of characteristics that occur together with a particularly high attrition rate? Describe the most notable combinations. | C26: gpt-5.6-luna | D26: 5 | G26: Ja | H26: Yes --> höhere Attrition | I26: folgt ursprünglicher Richtung
A27: E2_B02 | B27: Are there combinations of characteristics that occur together with a particularly high attrition rate? Describe the most notable combinations. | C27: gemini-3.6-flash | D27: 1 | G27: Ja | H27: Yes --> höhere Attrition | I27: folgt ursprünglicher Richtung
A28: E2_B02 | B28: Are there combinations of characteristics that occur together with a particularly high attrition rate? Describe the most notable combinations. | C28: gemini-3.6-flash | D28: 2 | G28: Ja | H28: Yes --> höhere Attrition | I28: folgt ursprünglicher Richtung
A29: E2_B02 | B29: Are there combinations of characteristics that occur together with a particularly high attrition rate? Describe the most notable combinations. | C29: gemini-3.6-flash | D29: 3 | G29: Ja | H29: Yes --> höhere Attrition | I29: folgt ursprünglicher Richtung
A30: E2_B02 | B30: Are there combinations of characteristics that occur together with a particularly high attrition rate? Describe the most notable combinations. | C30: gemini-3.6-flash | D30: 4 | G30: Ja | H30: Yes --> höhere Attrition | I30: folgt ursprünglicher Richtung
A31: E2_B02 | B31: Are there combinations of characteristics that occur together with a particularly high attrition rate? Describe the most notable combinations. | C31: gemini-3.6-flash | D31: 5 | G31: Ja | H31: Yes --> höhere Attrition | I31: folgt ursprünglicher Richtung
A32: E2_B03 | B32: Based on the data, which group of employees would you consider most at risk of leaving? Justify your answer. | C32: gpt-5.6-luna | D32: 1 | G32: Ja | H32: Yes --> höhere Attrition | I32: folgt ursprünglicher Richtung
A33: E2_B03 | B33: Based on the data, which group of employees would you consider most at risk of leaving? Justify your answer. | C33: gpt-5.6-luna | D33: 2 | G33: Ja | H33: Yes --> höhere Attrition | I33: folgt ursprünglicher Richtung
... A41: E2_B03 | B41: Based on the data, which group of employees would you consider most at risk of leaving? Justify your answer. | C41: gemini-3.6-flash | D41: 5 | G41: Ja | H41: Yes --> höhere Attrition | I41: folgt ursprünglicher Richtung
A42: E2_B04 | B42: What can you say about the relationship between income (MonthlyIncome) and attrition? Support your answer with the data. | C42: gpt-5.6-luna | D42: 1
A43: E2_B04 | B43: What can you say about the relationship between income (MonthlyIncome) and attrition? Support your answer with the data. | C43: gpt-5.6-luna | D43: 2
A44: E2_B04 | B44: What can you say about the relationship between income (MonthlyIncome) and attrition? Support your answer with the data. | C44: gpt-5.6-luna | D44: 3
A45: E2_B04 | B45: What can you say about the relationship between income (MonthlyIncome) and attrition? Support your answer with the data. | C45: gpt-5.6-luna | D45: 4
A46: E2_B04 | B46: What can you say about the relationship between income (MonthlyIncome) and attrition? Support your answer with the data. | C46: gpt-5.6-luna | D46: 5
A47: E2_B04 | B47: What can you say about the relationship between income (MonthlyIncome) and attrition? Support your answer with the data. | C47: gemini-3.6-flash | D47: 1
A48: E2_B04 | B48: What can you say about the relationship between income (MonthlyIncome) and attrition? Support your answer with the data. | C48: gemini-3.6-flash | D48: 2
A49: E2_B04 | B49: What can you say about the relationship between income (MonthlyIncome) and attrition? Support your answer with the data. | C49: gemini-3.6-flash | D49: 3
A50: E2_B04 | B50: What can you say about the relationship between income (MonthlyIncome) and attrition? Support your answer with the data. | C50: gemini-3.6-flash | D50: 4
A51: E2_B04 | B51: What can you say about the relationship between income (MonthlyIncome) and attrition? Support your answer with the data. | C51: gemini-3.6-flash | D51: 5
A52: E2_B05 | B52: Summarize the three most important findings from this dataset regarding employee attrition. | C52: gpt-5.6-luna | D52: 1 | G52: Ja | H52: Yes --> höhere Attrition | I52: folgt ursprünglicher Richtung
A53: E2_B05 | B53: Summarize the three most important findings from this dataset regarding employee attrition. | C53: gpt-5.6-luna | D53: 2 | G53: Ja | H53: Yes --> höhere Attrition | I53: folgt ursprünglicher Richtung
A54: E2_B05 | B54: Summarize the three most important findings from this dataset regarding employee attrition. | C54: gpt-5.6-luna | D54: 3 | G54: Ja | H54: Yes --> höhere Attrition | I54: folgt ursprünglicher Richtung
A55: E2_B05 | B55: Summarize the three most important findings from this dataset regarding employee attrition. | C55: gpt-5.6-luna | D55: 4 | G55: Ja | H55: Yes --> höhere Attrition | I55: folgt ursprünglicher Richtung
A56: E2_B05 | B56: Summarize the three most important findings from this dataset regarding employee attrition. | C56: gpt-5.6-luna | D56: 5 | G56: Ja | H56: Yes --> höhere Attrition | I56: folgt ursprünglicher Richtung
A57: E2_B05 | B57: Summarize the three most important findings from this dataset regarding employee attrition. | C57: gemini-3.6-flash | D57: 1 | G57: Ja | H57: Yes --> höhere Attrition | I57: folgt ursprünglicher Richtung
A58: E2_B05 | B58: Summarize the three most important findings from this dataset regarding employee attrition. | C58: gemini-3.6-flash | D58: 2 | G58: Ja | H58: Yes --> höhere Attrition | I58: folgt ursprünglicher Richtung
A59: E2_B05 | B59: Summarize the three most important findings from this dataset regarding employee attrition. | C59: gemini-3.6-flash | D59: 3 | G59: Ja | H59: Yes --> höhere Attrition | I59: folgt ursprünglicher Richtung
A60: E2_B05 | B60: Summarize the three most important findings from this dataset regarding employee attrition. | C60: gemini-3.6-flash | D60: 4 | G60: Ja | H60: Yes --> höhere Attrition | I60: folgt ursprünglicher Richtung
A61: E2_B05 | B61: Summarize the three most important findings from this dataset regarding employee attrition. | C61: gemini-3.6-flash | D61: 5 | F61: Based on an exploratory analysis of the provided employee dataset, here are the three most important findings regarding employee attrition:\n\n### 1. **Compensation and Job Level (Entry-Level Risk)**\n* **Finding:** Attrition is heavily concentrated among employees in **Job Level 1** who earn lower monthly incomes (predominantly below $4,000/month). \n* **Details:** Roles such as *Sales Representative*, *Laboratory Technician*, and *Research Scientist* show elevated turnover rates compared to higher job levels (*Manager*, *Research Director*), where attrition is minimal. Low pay and lower job levels are primary drivers of employee departure.\n\n### 2. **Tenure and Early-Career Flight Risk**\n* **Finding:** Employees in their early career stages—both in terms of age (under 30) and organizational tenure (0 to 3 total working years)—have significantly higher attrition rates.\n* **Details:** Employees who have been with the company or under their current manager for under 2 years are far more prone to leaving. Once employees pass the 5-year tenure mark, retention increases substantially.\n\n### 3. **Stock Option Incentives and Marital Status**\n* **Finding:** Employees with **no stock options (`StockOptionLevel = 0`)** and **Single employees** exhibit the highest turnover rates.\n* **Details:** Employees holding stock options (`StockOptionLevel` 1 or 2) and those who are married or divorced show much higher retention. The combination of financial equity incentives (stock options) and personal stability serves as a strong retention mechanism. | G61: Nein | H61: keine eindeutige Richtung | I61: uneindeutig | J61: OverTime wird unter den drei wichtigsten Ergebnissen nicht genannt; daher keine Aussage zur Richtung des manipulierten Zusammenhangs.
